[
  {
    "display_title": "Maple Leafs at Panthers",
    "title": "Maple Leafs at Panthers",
    "titleID": "B0DYXT4MZY",
    "synopsis": "Stanley Cup Playoffs: Watch the Toronto Maple Leafs and the Florida Panthers face off at Amerant Bank Arena broadcasting live from Sunrise!",
    "poster": "https://m.media-amazon.com/images/S/le-target-images-prod/amzn1.dv.gti.8074b6a2-3ab8-4a67-baf3-f0735341faa2/91/BOXART-16X9/en-US/1920x1080._UR1920,1080_.png",
    "liveinfo": "LIVE",
    "time_badge": "6:55 PM",
    "link": "/gp/video/detail/B0DYXT4MZY/ref=atv_hm_liv_lr4f4b5f_c_czP1UB_1_1?jic=8%7CEgNhbGw%3D",
    "status": "LIVE"
  },
  {
    "display_title": "Red Sox at Royals",
    "title": "Red Sox at Royals",
    "titleID": "B0DSHHRGBX",
    "synopsis": "Watch Red Sox at Royals LIVE from Kansas City.",
    "poster": "https://m.media-amazon.com/images/S/le-target-images-prod/amzn1.dv.gti.b80968a3-35a3-4764-a455-8a65e3465d07/155/BOXART-16X9/en-US._UR1920,1080_.png",
    "liveinfo": "LIVE",
    "time_badge": "7:40 PM",
    "link": "/gp/video/detail/B0DSHHRGBX/ref=atv_hm_liv_lr4f4b5f_c_czP1UB_1_2?jic=8%7CEgNhbGw%3D",
    "status": "LIVE"
  },
  {
    "display_title": "D.C. Defenders at San Antonio Brahmas",
    "title": "D.C. Defenders at San Antonio Brahmas",
    "titleID": "B0DQSPXZFX",
    "synopsis": "The Defenders take on the Brahmas",
    "poster": "https://m.media-amazon.com/images/S/le-target-images-prod/amzn1.dv.gti.c744881f-f273-468b-b7a6-11bdb4de227a/3/BOXART-16X9/en-US._UR1920,1080_.jpg",
    "liveinfo": "LIVE",
    "time_badge": "7:55 PM",
    "link": "/gp/video/detail/B0DQSPXZFX/ref=atv_hm_liv_lr4f4b5f_c_czP1UB_1_3?jic=8%7CEgNhbGw%3D",
    "status": "LIVE"
  },
  {
    "display_title": "Katzourakis vs. Cruz",
    "title": "Katzourakis vs. Cruz",
    "titleID": "B0F67BLKC7",
    "synopsis": "Enjoy a fantastic Overtime Boxing event in Houston, Texas, as Tournament Championship victor Andreas Katzourakis (15-0) looks to make a defence of his WBA Continental America’s super welterweight title.",
    "poster": "https://m.media-amazon.com/images/S/le-target-images-prod/amzn1.dv.gti.76d4c3f1-e4e7-4d52-a03c-271bf841b344/1/BOXART-16X9/en-US._UR1920,1080_.jpeg",
    "liveinfo": "LIVE",
    "time_badge": "7:57 PM",
    "link": "/gp/video/detail/B0F67BLKC7/ref=atv_hm_liv_lr4f4b5f_c_czP1UB_1_4?jic=8%7CEgNhbGw%3D",
    "status": "LIVE"
  },
  {
    "display_title": "Reds at Astros",
    "title": "Reds at Astros",
    "titleID": "B0BDTPTSRW",
    "synopsis": "Watch Reds at Astros LIVE from Houston.",
    "poster": "https://m.media-amazon.com/images/S/le-target-images-prod/amzn1.dv.gti.61679c3f-fc81-4e6c-afd3-d888f805a586/148/BOXART-16X9/en-US._UR1920,1080_.png",
    "liveinfo": "LIVE",
    "time_badge": "8:10 PM",
    "link": "/gp/video/detail/B0BDTPTSRW/ref=atv_hm_liv_lr4f4b5f_c_czP1UB_1_5?jic=8%7CEgNhbGw%3D",
    "status": "LIVE"
  },
  {
    "display_title": "MVP Prospects 12: Pero vs. Navarro",
    "title": "MVP Prospects 12: Pero vs. Navarro",
    "titleID": "B0F4XL82DD",
    "synopsis": "Most Valuable Promotions returns to Orlando, with undefeated Cuban Dainier Pero (10-0) facing Cesar Navarro (13-2) in a fantastic heavyweight main event.",
    "poster": "https://m.media-amazon.com/images/S/le-target-images-prod/amzn1.dv.gti.aa49f520-47cc-461f-9fa3-9a8e2a5414df/4/BOXART-16X9/en-US._UR1920,1080_.png",
    "liveinfo": "LIVE",
    "time_badge": "8:27 PM",
    "link": "/gp/video/detail/B0F4XL82DD/ref=atv_hm_liv_lr4f4b5f_c_czP1UB_1_6?jic=8%7CEgNhbGw%3D",
    "status": "LIVE"
  },
  {
    "display_title": "Padres at Rockies",
    "title": "Padres at Rockies",
    "titleID": "B0F3NGYD9Z",
    "synopsis": "Watch Padres at Rockies LIVE from Denver.",
    "poster": "https://m.media-amazon.com/images/S/le-target-images-prod/amzn1.dv.gti.70b8091f-b8a7-4bba-804e-bdab78c222b4/144/BOXART-16X9/en-US._UR1920,1080_.png",
    "liveinfo": "LIVE",
    "time_badge": "8:40 PM",
    "link": "/gp/video/detail/B0F3NGYD9Z/ref=atv_hm_liv_lr4f4b5f_c_czP1UB_1_7?jic=8%7CEgNhbGw%3D",
    "status": "LIVE"
  },
  {
    "display_title": "WHL Championship: Spokane Chiefs at Medicine Hat Tigers",
    "title": "WHL Championship: Spokane Chiefs at Medicine Hat Tigers",
    "titleID": "B0F5PJ41JW",
    "synopsis": "Game 1.",
    "poster": "https://m.media-amazon.com/images/S/le-target-images-prod/amzn1.dv.gti.ac2e6db6-a2ca-4fe8-9679-0764c11a7412/3/BOXART-16X9/en-US._UR1920,1080_.jpg",
    "liveinfo": "LIVE",
    "time_badge": "8:55 PM",
    "link": "/gp/video/detail/B0F5PJ41JW/ref=atv_hm_liv_lr4f4b5f_c_czP1UB_1_8?jic=8%7CEgNhbGw%3D",
    "status": "LIVE"
  },
  {
    "display_title": "Stars at Jets",
    "title": "Stars at Jets",
    "titleID": "B0DTCMBVVB",
    "synopsis": "Stanley Cup Playoffs: Watch the Dallas Stars and the Winnipeg Jets face off at Canada Life Centre broadcasting live from Winnipeg!",
    "poster": "https://m.media-amazon.com/images/S/le-target-images-prod/amzn1.dv.gti.9835a716-62a4-4cff-b011-c5798b0a1d21/104/BOXART-16X9/en-US/1920x1080._UR1920,1080_.png",
    "liveinfo": "LIVE",
    "time_badge": "9:25 PM",
    "link": "/gp/video/detail/B0DTCMBVVB/ref=atv_hm_liv_lr4f4b5f_c_czP1UB_1_9?jic=8%7CEgNhbGw%3D",
    "status": "LIVE"
  },
  {
    "display_title": "Toronto Blue Jays at Seattle Mariners",
    "title": "Toronto Blue Jays at Seattle Mariners",
    "titleID": "B0F5PBZCF3",
    "synopsis": "The West Coast Blue Jays fans take over T-Mobile Park in the opener against the Mariners.",
    "poster": "https://m.media-amazon.com/images/S/le-target-images-prod/amzn1.dv.gti.9adbd4c8-a1ba-4fcf-9b10-606c87fd9319/2/BOXART-16X9/en-US._UR1920,1080_.jpg",
    "liveinfo": "LIVE",
    "time_badge": "9:25 PM",
    "link": "/gp/video/detail/B0F5PBZCF3/ref=atv_hm_liv_lr4f4b5f_c_czP1UB_1_10?jic=8%7CEgNhbGw%3D",
    "status": "LIVE"
  },
  {
    "display_title": "Orioles at Angels",
    "title": "Orioles at Angels",
    "titleID": "B0F3VBGPGG",
    "synopsis": "Watch Orioles at Angels LIVE from Anaheim.",
    "poster": "https://m.media-amazon.com/images/S/le-target-images-prod/amzn1.dv.gti.dbd5115b-cca7-427e-b345-dea174faec30/143/BOXART-16X9/en-US._UR1920,1080_.png",
    "liveinfo": "LIVE",
    "time_badge": "9:38 PM",
    "link": "/gp/video/detail/B0F3VBGPGG/ref=atv_hm_liv_lr4f4b5f_c_czP1UB_1_11?jic=8%7CEgNhbGw%3D",
    "status": "LIVE"
  },
  {
    "display_title": "Dodgers at Diamondbacks",
    "title": "Dodgers at Diamondbacks",
    "titleID": "B0DQQ9BGGV",
    "synopsis": "Watch Dodgers at Diamondbacks LIVE from Phoenix.",
    "poster": "https://m.media-amazon.com/images/S/le-target-images-prod/amzn1.dv.gti.127d30d1-557d-4081-86fe-06a35437b758/123/BOXART-16X9/en-US._UR1920,1080_.png",
    "liveinfo": "LIVE",
    "time_badge": "9:40 PM",
    "link": "/gp/video/detail/B0DQQ9BGGV/ref=atv_hm_liv_lr4f4b5f_c_czP1UB_1_12?jic=8%7CEgNhbGw%3D",
    "status": "LIVE"
  },
  {
    "display_title": "Thunder at Nuggets",
    "title": "Thunder at Nuggets",
    "titleID": "B0F4TCGDLG",
    "synopsis": "NBA Playoffs: Watch the Oklahoma City Thunder and the Denver Nuggets face off at Ball Arena broadcasting live from Denver!",
    "poster": "https://m.media-amazon.com/images/S/le-target-images-prod/amzn1.dv.gti.5515d550-dd21-441d-bb71-78685538e7bb/31/BOXART-16X9/en-US/1920x1080._UR1920,1080_.png",
    "liveinfo": "LIVE",
    "time_badge": "9:55 PM",
    "link": "/gp/video/detail/B0F4TCGDLG/ref=atv_hm_liv_lr4f4b5f_c_czP1UB_1_13?jic=8%7CEgNhbGw%3D",
    "status": "LIVE"
  },
  {
    "display_title": "Yankees at Athletics",
    "title": "Yankees at Athletics",
    "titleID": "B0DYZ54XRF",
    "synopsis": "Watch Yankees at Athletics LIVE from West Sacramento.",
    "poster": "https://m.media-amazon.com/images/S/le-target-images-prod/amzn1.dv.gti.39603005-f348-44fa-b233-009479566361/141/BOXART-16X9/en-US._UR1920,1080_.png",
    "liveinfo": "LIVE",
    "time_badge": "10:05 PM",
    "link": "/gp/video/detail/B0DYZ54XRF/ref=atv_hm_liv_lr4f4b5f_c_czP1UB_1_14?jic=8%7CEgNhbGw%3D",
    "status": "LIVE"
  },
  {
    "display_title": " Angel City FC vs. Utah Royals",
    "title": " Angel City FC vs. Utah Royals",
    "titleID": "B0F5H8WQWD",
    "synopsis": " Watch Angel City FC host Utah Royals  at BMO Stadium broadcasting live from Los Angeles!",
    "poster": "https://m.media-amazon.com/images/S/le-target-images-prod/amzn1.dv.gti.81850cf7-c4ea-47ca-9e94-3a24ec11cfb0/22/BOXART-16X9/en-US/1920x1080._UR1920,1080_.png",
    "liveinfo": "LIVE",
    "time_badge": "10:25 PM",
    "link": "/gp/video/detail/B0F5H8WQWD/ref=atv_hm_liv_lr4f4b5f_c_czP1UB_1_15?jic=8%7CEgNhbGw%3D",
    "status": "LIVE"
  },
  {
    "display_title": "Melbourne vs. Hawthorn",
    "title": "Melbourne vs. Hawthorn",
    "titleID": "B0F63QBT85",
    "synopsis": "From Melbourne Cricket Ground in Melbourne, Victoria, Australia.",
    "poster": "https://m.media-amazon.com/images/S/le-target-images-prod/amzn1.dv.gti.51186ece-3a05-4a1f-a4e1-7191d02bf7d8/1/BOXART-16X9/en-US._UR1920,1080_.jpg",
    "liveinfo": "LIVE",
    "time_badge": "10:55 PM",
    "link": "/gp/video/detail/B0F63QBT85/ref=atv_hm_liv_lr4f4b5f_c_czP1UB_1_16?jic=8%7CEgNhbGw%3D",
    "status": "LIVE"
  },
  {
    "display_title": "Pacific Four Series: New Zealand at Australia",
    "title": "Pacific Four Series: New Zealand at Australia",
    "titleID": "B0F1F6XNJK",
    "synopsis": "From McDonald Jones Stadium in Newcastle, New South Wales, Australia.",
    "poster": "https://m.media-amazon.com/images/S/le-target-images-prod/amzn1.dv.gti.0fba2ead-6249-4e71-b26c-cd06991ca61b/2/BOXART-16X9/en-US._UR1920,1080_.jpg",
    "liveinfo": "UPCOMING",
    "time_badge": "Tomorrow 12:55 AM",
    "link": "/gp/video/detail/B0F1F6XNJK/ref=atv_hm_liv_lr4f4b5f_c_czP1UB_1_17?jic=8%7CEgNhbGw%3D",
    "status": "UPCOMING"
  },
  {
    "display_title": "Essendon vs. Sydney Swans",
    "title": "Essendon vs. Sydney Swans",
    "titleID": "B0F5MJCZG8",
    "synopsis": "From Marvel Stadium in Melbourne, Australia.",
    "poster": "https://m.media-amazon.com/images/S/le-target-images-prod/amzn1.dv.gti.7f3e06f9-baab-4023-96e2-3e7cebebed98/1/BOXART-16X9/en-US._UR1920,1080_.jpg",
    "liveinfo": "UPCOMING",
    "time_badge": "Tomorrow 1:55 AM",
    "link": "/gp/video/detail/B0F5MJCZG8/ref=atv_hm_liv_lr4f4b5f_c_czP1UB_1_18?jic=8%7CEgNhbGw%3D",
    "status": "UPCOMING"
  },
  {
    "display_title": "PTT Austria Women - Day 6",
    "title": "PTT Austria Women - Day 6",
    "titleID": "B0F3LN32D1",
    "synopsis": "PTT Austria Women - Day 6",
    "poster": "https://m.media-amazon.com/images/S/le-target-images-prod/amzn1.dv.gti.99b5e6b3-122f-4fe3-941d-8f98d727abcf/1/BOXART-16X9/en-US._UR1920,1080_.png",
    "liveinfo": "UPCOMING",
    "time_badge": "Tomorrow 2:55 AM",
    "link": "/gp/video/detail/B0F3LN32D1/ref=atv_hm_liv_lr4f4b5f_c_czP1UB_1_19?jic=8%7CEgNhbGw%3D",
    "status": "UPCOMING"
  },
  {
    "display_title": "PTT North Macedonia Men - Day 6",
    "title": "PTT North Macedonia Men - Day 6",
    "titleID": "B0DXP977ZS",
    "synopsis": "PTT North Macedonia Men - Day 6",
    "poster": "https://m.media-amazon.com/images/S/le-target-images-prod/amzn1.dv.gti.cfc01125-0ee0-4c43-a8b6-5bdcdd068427/1/BOXART-16X9/en-US._UR1920,1080_.png",
    "liveinfo": "UPCOMING",
    "time_badge": "Tomorrow 2:55 AM",
    "link": "/gp/video/detail/B0DXP977ZS/ref=atv_hm_liv_lr4f4b5f_c_czP1UB_1_20?jic=8%7CEgNhbGw%3D",
    "status": "UPCOMING"
  },
  {
    "display_title": "Crusaders vs. Chiefs",
    "title": "Crusaders vs. Chiefs",
    "titleID": "B0F6JB34HF",
    "synopsis": "From Apollo Projects Stadium in Christchurch, Canterbury, New Zealand.",
    "poster": "https://m.media-amazon.com/images/S/le-target-images-prod/amzn1.dv.gti.e32b0bff-b347-4f5d-bcd3-754b11d0594e/1/BOXART-16X9/en-US._UR1920,1080_.jpg",
    "liveinfo": "UPCOMING",
    "time_badge": "Tomorrow 3:00 AM",
    "link": "/gp/video/detail/B0F6JB34HF/ref=atv_hm_liv_c_czP1UB_1_21?jic=8%7CEgNhbGw%3D",
    "status": "UPCOMING"
  },
  {
    "display_title": "Spa - Race 2",
    "title": "Spa - Race 2",
    "titleID": "B0F2M9LKK2",
    "synopsis": "Watch all the latest racing action live on DAZN.",
    "poster": "https://m.media-amazon.com/images/S/le-target-images-prod/amzn1.dv.gti.9614d0cc-ebc6-41e4-9ba8-fd2735d97224/1/BOXART-16X9/en-US._UR1920,1080_.png",
    "liveinfo": "UPCOMING",
    "time_badge": "Tomorrow 3:10 AM",
    "link": "/gp/video/detail/B0F2M9LKK2/ref=atv_hm_liv_c_czP1UB_1_22?jic=8%7CEgNhbGw%3D",
    "status": "UPCOMING"
  },
  {
    "display_title": "PTT Portugal Women - Day 6",
    "title": "PTT Portugal Women - Day 6",
    "titleID": "B0F3VCYDKD",
    "synopsis": "PTT Portugal Women - Day 6",
    "poster": "https://m.media-amazon.com/images/S/le-target-images-prod/amzn1.dv.gti.38144daf-92f7-4fe8-99cf-21a8d9d4e1c4/1/BOXART-16X9/en-US._UR1920,1080_.png",
    "liveinfo": "UPCOMING",
    "time_badge": "Tomorrow 3:55 AM",
    "link": "/gp/video/detail/B0F3VCYDKD/ref=atv_hm_liv_c_czP1UB_1_23?jic=8%7CEgNhbGw%3D",
    "status": "UPCOMING"
  },
  {
    "display_title": "PTT Portugal Men - Day 6",
    "title": "PTT Portugal Men - Day 6",
    "titleID": "B0F4P1YG94",
    "synopsis": "PTT Portugal Men - Day 6",
    "poster": "https://m.media-amazon.com/images/S/le-target-images-prod/amzn1.dv.gti.69b48273-285a-4f0d-be3e-cc38c4e562fc/1/BOXART-16X9/en-US._UR1920,1080_.png",
    "liveinfo": "UPCOMING",
    "time_badge": "Tomorrow 3:55 AM",
    "link": "/gp/video/detail/B0F4P1YG94/ref=atv_hm_liv_c_czP1UB_1_24?jic=8%7CEgNhbGw%3D",
    "status": "UPCOMING"
  },
  {
    "display_title": "ATP, Day 4: Court 14",
    "title": "ATP, Day 4: Court 14",
    "titleID": "B0F5PWBZTH",
    "synopsis": "From Foro Italico in Rome.",
    "poster": "https://m.media-amazon.com/images/S/le-target-images-prod/amzn1.dv.gti.25fb76ed-3f3a-41bf-ac75-d87811fa284d/4/BOXART-16X9/en-US._UR1920,1080_.jpg",
    "liveinfo": "UPCOMING",
    "time_badge": "Tomorrow 4:55 AM",
    "link": "/gp/video/detail/B0F5PWBZTH/ref=atv_hm_liv_c_czP1UB_1_25?jic=8%7CEgNhbGw%3D",
    "status": "UPCOMING"
  },
  {
    "display_title": "ATP, Day 4: Campo Centrale",
    "title": "ATP, Day 4: Campo Centrale",
    "titleID": "B0F39817NM",
    "synopsis": "From Foro Italico in Rome.",
    "poster": "https://m.media-amazon.com/images/S/le-target-images-prod/amzn1.dv.gti.5c171dd1-cc65-467b-8c35-552c6cac8a5d/4/BOXART-16X9/en-US._UR1920,1080_.jpg",
    "liveinfo": "UPCOMING",
    "time_badge": "Tomorrow 4:55 AM",
    "link": "/gp/video/detail/B0F39817NM/ref=atv_hm_liv_c_czP1UB_1_26?jic=8%7CEgNhbGw%3D",
    "status": "UPCOMING"
  },
  {
    "display_title": "ATP, Day 4: Court 1",
    "title": "ATP, Day 4: Court 1",
    "titleID": "B0DR1ZVT9N",
    "synopsis": "From Foro Italico in Rome.",
    "poster": "https://m.media-amazon.com/images/S/le-target-images-prod/amzn1.dv.gti.6cc4a7b1-7085-48b7-ad0e-7a426ec71f72/4/BOXART-16X9/en-US._UR1920,1080_.jpg",
    "liveinfo": "UPCOMING",
    "time_badge": "Tomorrow 4:55 AM",
    "link": "/gp/video/detail/B0DR1ZVT9N/ref=atv_hm_liv_c_czP1UB_1_27?jic=8%7CEgNhbGw%3D",
    "status": "UPCOMING"
  },
  {
    "display_title": "ATP, Day 4: Super Tennis",
    "title": "ATP, Day 4: Super Tennis",
    "titleID": "B0F58Q4DGT",
    "synopsis": "From Foro Italico in Rome.",
    "poster": "https://m.media-amazon.com/images/S/le-target-images-prod/amzn1.dv.gti.7e6a6a15-9f2b-4583-8324-f42f9e01bcd0/5/BOXART-16X9/en-US._UR1920,1080_.jpg",
    "liveinfo": "UPCOMING",
    "time_badge": "Tomorrow 4:55 AM",
    "link": "/gp/video/detail/B0F58Q4DGT/ref=atv_hm_liv_c_czP1UB_1_28?jic=8%7CEgNhbGw%3D",
    "status": "UPCOMING"
  },
  {
    "display_title": "WTA Early Round Coverage, Day 4",
    "title": "WTA Early Round Coverage, Day 4",
    "titleID": "B0DR6HP9B8",
    "synopsis": "From Foro Italico in Rome.",
    "poster": "https://m.media-amazon.com/images/S/le-target-images-prod/amzn1.dv.gti.7f3ccb5b-46e6-48ea-b213-a9eadcae8c61/5/BOXART-16X9/en-US._UR1920,1080_.jpg",
    "liveinfo": "UPCOMING",
    "time_badge": "Tomorrow 4:55 AM",
    "link": "/gp/video/detail/B0DR6HP9B8/ref=atv_hm_liv_c_czP1UB_1_29?jic=8%7CEgNhbGw%3D",
    "status": "UPCOMING"
  },
  {
    "display_title": "ATP Early Round Coverage, Day 4",
    "title": "ATP Early Round Coverage, Day 4",
    "titleID": "B0F3KYLN6C",
    "synopsis": "From Foro Italico in Rome.",
    "poster": "https://m.media-amazon.com/images/S/le-target-images-prod/amzn1.dv.gti.9e97fc4a-78a7-463d-806a-62d64c886779/5/BOXART-16X9/en-US._UR1920,1080_.jpg",
    "liveinfo": "UPCOMING",
    "time_badge": "Tomorrow 4:55 AM",
    "link": "/gp/video/detail/B0F3KYLN6C/ref=atv_hm_liv_c_czP1UB_1_30?jic=8%7CEgNhbGw%3D",
    "status": "UPCOMING"
  },
  {
    "display_title": "PTT North Macedonia Men - Day 7",
    "title": "PTT North Macedonia Men - Day 7",
    "titleID": "B0DTNGH64C",
    "synopsis": "PTT North Macedonia Men - Day 7",
    "poster": "https://m.media-amazon.com/images/S/le-target-images-prod/amzn1.dv.gti.76148380-1e80-48df-b070-2cbbf8ba3ad9/1/BOXART-16X9/en-US._UR1920,1080_.png",
    "liveinfo": "UPCOMING",
    "time_badge": "Sun, May 11 2:55 AM",
    "link": "/gp/video/detail/B0DTNGH64C/ref=atv_hm_liv_c_czP1UB_1_141?jic=8%7CEgNhbGw%3D",
    "status": "UPCOMING"
  },
  {
    "display_title": "PTT Portugal Women - Day 7",
    "title": "PTT Portugal Women - Day 7",
    "titleID": "B0F6574B9Y",
    "synopsis": "PTT Portugal Women - Day 7",
    "poster": "https://m.media-amazon.com/images/S/le-target-images-prod/amzn1.dv.gti.e7339273-c364-4a9d-b679-657dd4660ff5/1/BOXART-16X9/en-US._UR1920,1080_.png",
    "liveinfo": "UPCOMING",
    "time_badge": "Sun, May 11 3:55 AM",
    "link": "/gp/video/detail/B0F6574B9Y/ref=atv_hm_liv_c_czP1UB_1_142?jic=8%7CEgNhbGw%3D",
    "status": "UPCOMING"
  },
  {
    "display_title": "PTT Portugal Men - Day 7",
    "title": "PTT Portugal Men - Day 7",
    "titleID": "B0DFNJ7R54",
    "synopsis": "PTT Portugal Men - Day 7",
    "poster": "https://m.media-amazon.com/images/S/le-target-images-prod/amzn1.dv.gti.ed8f15a9-3aab-4dc0-b0e2-a91265fe5617/1/BOXART-16X9/en-US._UR1920,1080_.png",
    "liveinfo": "UPCOMING",
    "time_badge": "Sun, May 11 3:55 AM",
    "link": "/gp/video/detail/B0DFNJ7R54/ref=atv_hm_liv_c_czP1UB_1_143?jic=8%7CEgNhbGw%3D",
    "status": "UPCOMING"
  },
  {
    "display_title": "ATP/WTA Early Round Coverage, Day 5",
    "title": "ATP/WTA Early Round Coverage, Day 5",
    "titleID": "B0DPR9CRKY",
    "synopsis": "From Foro Italico in Rome.",
    "poster": "https://m.media-amazon.com/images/S/le-target-images-prod/amzn1.dv.gti.0dcaf302-11ed-4691-96b7-e0408b44d564/7/BOXART-16X9/en-US._UR1920,1080_.jpg",
    "liveinfo": "UPCOMING",
    "time_badge": "Sun, May 11 4:55 AM",
    "link": "/gp/video/detail/B0DPR9CRKY/ref=atv_hm_liv_c_czP1UB_1_144?jic=8%7CEgNhbGw%3D",
    "status": "UPCOMING"
  },
  {
    "display_title": "WTA Early Round Coverage, Day 5",
    "title": "WTA Early Round Coverage, Day 5",
    "titleID": "B0DSJNFT3X",
    "synopsis": "From Foro Italico in Rome.",
    "poster": "https://m.media-amazon.com/images/S/le-target-images-prod/amzn1.dv.gti.51dddfb7-a712-4668-b5c6-a65d36f9970a/13/BOXART-16X9/en-US._UR1920,1080_.jpg",
    "liveinfo": "UPCOMING",
    "time_badge": "Sun, May 11 4:55 AM",
    "link": "/gp/video/detail/B0DSJNFT3X/ref=atv_hm_liv_c_czP1UB_1_145?jic=8%7CEgNhbGw%3D",
    "status": "UPCOMING"
  },
  {
    "display_title": "ATP, Day 5: Grand Stand",
    "title": "ATP, Day 5: Grand Stand",
    "titleID": "B0F233SDQ8",
    "synopsis": "From Foro Italico in Rome.",
    "poster": "https://m.media-amazon.com/images/S/le-target-images-prod/amzn1.dv.gti.5a2e3156-d1e3-484c-9db8-36c6c58dd7f7/5/BOXART-16X9/en-US._UR1920,1080_.jpg",
    "liveinfo": "UPCOMING",
    "time_badge": "Sun, May 11 4:55 AM",
    "link": "/gp/video/detail/B0F233SDQ8/ref=atv_hm_liv_c_czP1UB_1_146?jic=8%7CEgNhbGw%3D",
    "status": "UPCOMING"
  },
  {
    "display_title": "ATP 1000 Tennis: Rome: Early Round Coverage Day 5",
    "title": "ATP 1000 Tennis: Rome: Early Round Coverage Day 5",
    "titleID": "B0F3VLJ1WL",
    "synopsis": "From Foro Italico in Rome.",
    "poster": "https://m.media-amazon.com/images/S/le-target-images-prod/amzn1.dv.gti.72b6416b-8cc1-4d6d-980b-47eebb8bbcc2/2/BOXART-16X9/en-US._UR1920,1080_.jpg",
    "liveinfo": "UPCOMING",
    "time_badge": "Sun, May 11 4:55 AM",
    "link": "/gp/video/detail/B0F3VLJ1WL/ref=atv_hm_liv_c_czP1UB_1_147?jic=8%7CEgNhbGw%3D",
    "status": "UPCOMING"
  },
  {
    "display_title": "Rome Open - Day 6",
    "title": "Rome Open - Day 6",
    "titleID": "B0F5MHSGG3",
    "synopsis": "DAZN brings you all the WTA action as the matches continue live from the Rome Open",
    "poster": "https://m.media-amazon.com/images/S/le-target-images-prod/amzn1.dv.gti.535a0ee0-cdd3-4e95-8677-ac430a88fba7/2/BOXART-16X9/en-US._UR1920,1080_.png",
    "liveinfo": "UPCOMING",
    "time_badge": "Sun, May 11 4:57 AM",
    "link": "/gp/video/detail/B0F5MHSGG3/ref=atv_hm_liv_c_czP1UB_1_148?jic=8%7CEgNhbGw%3D",
    "status": "UPCOMING"
  },
  {
    "display_title": "Real Betis vs. Barcelona",
    "title": "Real Betis vs. Barcelona",
    "titleID": "B0F6BC9P9G",
    "synopsis": "Watch Real Betis take on Barcelona in Liga F.\n\n \n",
    "poster": "https://m.media-amazon.com/images/S/le-target-images-prod/amzn1.dv.gti.265c5d63-a70a-4e65-aa94-f3a5d91a7780/2/BOXART-16X9/en-US._UR1920,1080_.png",
    "liveinfo": "UPCOMING",
    "time_badge": "Sun, May 11 5:43 AM",
    "link": "/gp/video/detail/B0F6BC9P9G/ref=atv_hm_liv_c_czP1UB_1_149?jic=8%7CEgNhbGw%3D",
    "status": "UPCOMING"
  },
  {
    "display_title": "Levante vs. Madrid CFF",
    "title": "Levante vs. Madrid CFF",
    "titleID": "B0F7XJKHP4",
    "synopsis": "Watch Levante take on Madrid CFF in Liga F.",
    "poster": "https://m.media-amazon.com/images/S/le-target-images-prod/amzn1.dv.gti.d8693174-5666-47c8-8300-d606f0cb82aa/1/BOXART-16X9/en-US._UR1920,1080_.png",
    "liveinfo": "UPCOMING",
    "time_badge": "Sun, May 11 5:43 AM",
    "link": "/gp/video/detail/B0F7XJKHP4/ref=atv_hm_liv_c_czP1UB_1_150?jic=8%7CEgNhbGw%3D",
    "status": "UPCOMING"
  },
  {
    "display_title": "ATP, Day 4: Pietrangeli",
    "title": "ATP, Day 4: Pietrangeli",
    "titleID": "B0F1FCBBRW",
    "synopsis": "From Foro Italico in Rome.",
    "poster": "https://m.media-amazon.com/images/S/le-target-images-prod/amzn1.dv.gti.b2621f31-cdba-42e7-a0ad-8dad1a06cb40/5/BOXART-16X9/en-US._UR1920,1080_.jpg",
    "liveinfo": "UPCOMING",
    "time_badge": "Tomorrow 4:55 AM",
    "link": "/gp/video/detail/B0F1FCBBRW/ref=atv_hm_liv_c_czP1UB_1_31?jic=8%7CEgNhbGw%3D",
    "status": "UPCOMING"
  },
  {
    "display_title": "WTA Early Round Coverage, Day 4",
    "title": "WTA Early Round Coverage, Day 4",
    "titleID": "B0F4XPP2T6",
    "synopsis": "From Foro Italico in Rome.",
    "poster": "https://m.media-amazon.com/images/S/le-target-images-prod/amzn1.dv.gti.f87982cd-0abe-4371-970d-735c60b2ff57/6/BOXART-16X9/en-US._UR1920,1080_.jpg",
    "liveinfo": "UPCOMING",
    "time_badge": "Tomorrow 4:55 AM",
    "link": "/gp/video/detail/B0F4XPP2T6/ref=atv_hm_liv_c_czP1UB_1_32?jic=8%7CEgNhbGw%3D",
    "status": "UPCOMING"
  },
  {
    "display_title": "Rome Open - Day 5",
    "title": "Rome Open - Day 5",
    "titleID": "B0DR5DJHJM",
    "synopsis": "DAZN brings you all the WTA action as the matches continue live from the Rome Open.",
    "poster": "https://m.media-amazon.com/images/S/le-target-images-prod/amzn1.dv.gti.fde70dae-b877-4bd5-bcdc-5775d23c4534/2/BOXART-16X9/en-US._UR1920,1080_.png",
    "liveinfo": "UPCOMING",
    "time_badge": "Tomorrow 4:57 AM",
    "link": "/gp/video/detail/B0DR5DJHJM/ref=atv_hm_liv_c_czP1UB_1_33?jic=8%7CEgNhbGw%3D",
    "status": "UPCOMING"
  },
  {
    "display_title": "Western Force vs. Brumbies",
    "title": "Western Force vs. Brumbies",
    "titleID": "B0DKN7JK44",
    "synopsis": "From HBF Park in Perth, Australia.",
    "poster": "https://m.media-amazon.com/images/S/le-target-images-prod/amzn1.dv.gti.501c1061-39b7-4783-879d-4c8e9f5635d3/1/BOXART-16X9/en-US._UR1920,1080_.jpg",
    "liveinfo": "UPCOMING",
    "time_badge": "Tomorrow 5:30 AM",
    "link": "/gp/video/detail/B0DKN7JK44/ref=atv_hm_liv_c_czP1UB_1_34?jic=8%7CEgNhbGw%3D",
    "status": "UPCOMING"
  },
  {
    "display_title": "ATP, Day 4: Grand Stand",
    "title": "ATP, Day 4: Grand Stand",
    "titleID": "B0DCFKVZTT",
    "synopsis": "From Foro Italico in Rome.",
    "poster": "https://m.media-amazon.com/images/S/le-target-images-prod/amzn1.dv.gti.24436020-94d2-4347-96d4-c56c35e109b0/6/BOXART-16X9/en-US._UR1920,1080_.jpg",
    "liveinfo": "UPCOMING",
    "time_badge": "Tomorrow 5:55 AM",
    "link": "/gp/video/detail/B0DCFKVZTT/ref=atv_hm_liv_c_czP1UB_1_35?jic=8%7CEgNhbGw%3D",
    "status": "UPCOMING"
  },
  {
    "display_title": "Slovenia vs. Canada",
    "title": "Slovenia vs. Canada",
    "titleID": "B0DGDSK85V",
    "synopsis": "Group A.",
    "poster": "https://m.media-amazon.com/images/S/le-target-images-prod/amzn1.dv.gti.4153a7f8-0118-4b2a-8b30-36003f1af542/174/BOXART-16X9/en-US._UR1920,1080_.jpg",
    "liveinfo": "UPCOMING",
    "time_badge": "Tomorrow 5:55 AM",
    "link": "/gp/video/detail/B0DGDSK85V/ref=atv_hm_liv_c_czP1UB_1_36?jic=8%7CEgNhbGw%3D",
    "status": "UPCOMING"
  },
  {
    "display_title": "Norway vs. Kazakhstan",
    "title": "Norway vs. Kazakhstan",
    "titleID": "B0F5PKYN7J",
    "synopsis": "Group B.",
    "poster": "https://m.media-amazon.com/images/S/le-target-images-prod/amzn1.dv.gti.e28dac17-693b-4254-a224-8b06c3368112/6/BOXART-16X9/en-US._UR1920,1080_.jpg",
    "liveinfo": "UPCOMING",
    "time_badge": "Tomorrow 5:55 AM",
    "link": "/gp/video/detail/B0F5PKYN7J/ref=atv_hm_liv_c_czP1UB_1_37?jic=8%7CEgNhbGw%3D",
    "status": "UPCOMING"
  },
  {
    "display_title": "2025 Internazionali BNL d'Italia Tennis",
    "title": "2025 Internazionali BNL d'Italia Tennis",
    "titleID": "B0DX89CM15",
    "synopsis": "From Foro Italico in Rome.",
    "poster": "https://m.media-amazon.com/images/S/le-target-images-prod/amzn1.dv.gti.7422ccad-6472-42be-ae28-b009843aac85/4/BOXART-16X9/en-US._UR1920,1080_.jpg",
    "liveinfo": "UPCOMING",
    "time_badge": "Tomorrow 6:55 AM",
    "link": "/gp/video/detail/B0DX89CM15/ref=atv_hm_liv_c_czP1UB_1_38?jic=8%7CEgNhbGw%3D",
    "status": "UPCOMING"
  },
  {
    "display_title": "Leyton Orient vs. Stockport",
    "title": "Leyton Orient vs. Stockport",
    "titleID": "B0DHCCYW7Y",
    "synopsis": "Catch all the latest League One action live on DAZN.",
    "poster": "https://m.media-amazon.com/images/S/le-target-images-prod/amzn1.dv.gti.c7e5d66a-f2f8-4abf-8ace-e9189ff445d1/1/BOXART-16X9/en-US._UR1920,1080_.png",
    "liveinfo": "UPCOMING",
    "time_badge": "Tomorrow 7:14 AM",
    "link": "/gp/video/detail/B0DHCCYW7Y/ref=atv_hm_liv_c_czP1UB_1_39?jic=8%7CEgNhbGw%3D",
    "status": "UPCOMING"
  },
  {
    "display_title": "Valencia CF vs. Getafe CF",
    "title": "Valencia CF vs. Getafe CF",
    "titleID": "B0DQVP8H82",
    "synopsis": "Watch Valencia CF take on Getafe CF",
    "poster": "https://m.media-amazon.com/images/S/le-target-images-prod/amzn1.dv.gti.379c2129-f4b3-453a-930b-d2f0577054d1/23/BOXART-16X9/en-US._UR1920,1080_.jpg",
    "liveinfo": "UPCOMING",
    "time_badge": "Tomorrow 7:49 AM",
    "link": "/gp/video/detail/B0DQVP8H82/ref=atv_hm_liv_c_czP1UB_1_40?jic=8%7CEgNhbGw%3D",
    "status": "UPCOMING"
  },
  {
    "display_title": "FC Dallas vs. Real Salt Lake",
    "title": "FC Dallas vs. Real Salt Lake",
    "titleID": "B0F63SFKZ9",
    "synopsis": "Watch Dallas host RSL",
    "poster": "https://m.media-amazon.com/images/S/le-target-images-prod/amzn1.dv.gti.4bb6e454-613c-4197-947e-5960d29c0e7f/2/BOXART-16X9/en-US/1920x1080._UR1920,1080_.png",
    "liveinfo": "UPCOMING",
    "time_badge": "Tomorrow 8:30 PM",
    "link": "/gp/video/detail/B0F63SFKZ9/ref=atv_hm_liv_c_czP1UB_1_131?jic=8%7CEgNhbGw%3D",
    "status": "UPCOMING"
  },
  {
    "display_title": "Golden Knights at Oilers",
    "title": "Golden Knights at Oilers",
    "titleID": "B0DZC8XHKQ",
    "synopsis": "Stanley Cup Playoffs: Watch the Vegas Golden Knights and the Edmonton Oilers face off at Rogers Place broadcasting live from Edmonton!",
    "poster": "https://m.media-amazon.com/images/S/le-target-images-prod/amzn1.dv.gti.51834af4-07d2-4b3f-a3ac-521f1e72e35e/107/BOXART-16X9/en-US/1920x1080._UR1920,1080_.png",
    "liveinfo": "UPCOMING",
    "time_badge": "Tomorrow 8:55 PM",
    "link": "/gp/video/detail/B0DZC8XHKQ/ref=atv_hm_liv_c_czP1UB_1_132?jic=8%7CEgNhbGw%3D",
    "status": "UPCOMING"
  },
  {
    "display_title": "Houston Hitmen vs. LA Elite & Phoenix Fury vs. Las Vegas Hustle",
    "title": "Houston Hitmen vs. LA Elite & Phoenix Fury vs. Las Vegas Hustle",
    "titleID": "B0F7NTVJ16",
    "synopsis": "Enjoy more Team Combat League action on DAZN.\n",
    "poster": "https://m.media-amazon.com/images/S/le-target-images-prod/amzn1.dv.gti.9eb99e02-ddf5-458c-9b04-129727f033a0/1/BOXART-16X9/en-US._UR1920,1080_.png",
    "liveinfo": "UPCOMING",
    "time_badge": "Tomorrow 8:57 PM",
    "link": "/gp/video/detail/B0F7NTVJ16/ref=atv_hm_liv_c_czP1UB_1_133?jic=8%7CEgNhbGw%3D",
    "status": "UPCOMING"
  },
  {
    "display_title": "Toronto Blue Jays at Seattle Mariners",
    "title": "Toronto Blue Jays at Seattle Mariners",
    "titleID": "B0F67J2R67",
    "synopsis": "The Mariners send out rookie Logan Evans in the second of a three-game series with the Blue Jays.",
    "poster": "https://m.media-amazon.com/images/S/le-target-images-prod/amzn1.dv.gti.add1f1bb-e29e-4f00-86cb-d1a98640c5ba/2/BOXART-16X9/en-US._UR1920,1080_.jpg",
    "liveinfo": "UPCOMING",
    "time_badge": "Tomorrow 9:25 PM",
    "link": "/gp/video/detail/B0F67J2R67/ref=atv_hm_liv_c_czP1UB_1_134?jic=8%7CEgNhbGw%3D",
    "status": "UPCOMING"
  },
  {
    "display_title": "Halifax Thunderbirds at Saskatchewan Rush",
    "title": "Halifax Thunderbirds at Saskatchewan Rush",
    "titleID": "B0F32734KD",
    "synopsis": "Semifinal, Game 2.",
    "poster": "https://m.media-amazon.com/images/S/le-target-images-prod/amzn1.dv.gti.e7de1992-7f29-408a-ae55-9bef364b111b/20/BOXART-16X9/en-US._UR1920,1080_.jpg",
    "liveinfo": "UPCOMING",
    "time_badge": "Tomorrow 9:25 PM",
    "link": "/gp/video/detail/B0F32734KD/ref=atv_hm_liv_c_czP1UB_1_135?jic=8%7CEgNhbGw%3D",
    "status": "UPCOMING"
  },
  {
    "display_title": "Orioles at Angels",
    "title": "Orioles at Angels",
    "titleID": "B0F5SQ8F1H",
    "synopsis": "Watch Orioles at Angels LIVE from Anaheim.",
    "poster": "https://m.media-amazon.com/images/S/le-target-images-prod/amzn1.dv.gti.7db4ee24-b4b6-4716-b37e-1d0567d22380/106/BOXART-16X9/en-US._UR1920,1080_.png",
    "liveinfo": "UPCOMING",
    "time_badge": "Tomorrow 9:38 PM",
    "link": "/gp/video/detail/B0F5SQ8F1H/ref=atv_hm_liv_c_czP1UB_1_136?jic=8%7CEgNhbGw%3D",
    "status": "UPCOMING"
  },
  {
    "display_title": "Emanuel Navarrete vs. Charly Suarez",
    "title": "Emanuel Navarrete vs. Charly Suarez",
    "titleID": "B0F4KVSN6K",
    "synopsis": "From Pechanga Arena in San Diego.",
    "poster": "https://m.media-amazon.com/images/S/le-target-images-prod/amzn1.dv.gti.8691fc92-b1e5-4176-8b5f-3125b5c11a09/10/BOXART-16X9/en-US._UR1920,1080_.jpg",
    "liveinfo": "UPCOMING",
    "time_badge": "Tomorrow 9:55 PM",
    "link": "/gp/video/detail/B0F4KVSN6K/ref=atv_hm_liv_c_czP1UB_1_137?jic=8%7CEgNhbGw%3D",
    "status": "UPCOMING"
  },
  {
    "display_title": "Portland Timbers vs. Sporting Kansas City",
    "title": "Portland Timbers vs. Sporting Kansas City",
    "titleID": "B0DP6BSRZF",
    "synopsis": "Watch Portland Timbers host Sporting Kansas City  at Providence Park broadcasting live from Portland!",
    "poster": "https://m.media-amazon.com/images/S/le-target-images-prod/amzn1.dv.gti.cf620208-a2f3-4a9e-8ed4-3bcf372048d7/16/BOXART-16X9/en-US/1920x1080._UR1920,1080_.png",
    "liveinfo": "UPCOMING",
    "time_badge": "Tomorrow 10:25 PM",
    "link": "/gp/video/detail/B0DP6BSRZF/ref=atv_hm_liv_c_czP1UB_1_138?jic=8%7CEgNhbGw%3D",
    "status": "UPCOMING"
  },
  {
    "display_title": "Red Bull Rookies Cup - Day 2 Le Mans",
    "title": "Red Bull Rookies Cup - Day 2 Le Mans",
    "titleID": "B0F28RQ7QS",
    "synopsis": "Watch the latest action from Red Bull TV.",
    "poster": "https://m.media-amazon.com/images/S/le-target-images-prod/amzn1.dv.gti.bd8293ed-3e1f-4dae-90f8-3a8c6f052d48/2/BOXART-16X9/en-US._UR1920,1080_.png",
    "liveinfo": "UPCOMING",
    "time_badge": "Sun, May 11 2:35 AM",
    "link": "/gp/video/detail/B0F28RQ7QS/ref=atv_hm_liv_c_czP1UB_1_139?jic=8%7CEgNhbGw%3D",
    "status": "UPCOMING"
  },
  {
    "display_title": "PTT Austria Women - Day 7",
    "title": "PTT Austria Women - Day 7",
    "titleID": "B0F5BNFWQM",
    "synopsis": "PTT Austria Women - Day 7",
    "poster": "https://m.media-amazon.com/images/S/le-target-images-prod/amzn1.dv.gti.1321ce07-c83e-44e9-982d-0113c8399f9e/1/BOXART-16X9/en-US._UR1920,1080_.png",
    "liveinfo": "UPCOMING",
    "time_badge": "Sun, May 11 2:55 AM",
    "link": "/gp/video/detail/B0F5BNFWQM/ref=atv_hm_liv_c_czP1UB_1_140?jic=8%7CEgNhbGw%3D",
    "status": "UPCOMING"
  },
  {
    "display_title": "Oshawa Generals at London Knights",
    "title": "Oshawa Generals at London Knights",
    "titleID": "B0DNYTLS76",
    "synopsis": "From Canada Life Place in London, Ontario, Canada.",
    "poster": "https://m.media-amazon.com/images/S/le-target-images-prod/amzn1.dv.gti.d13e40b2-24b0-4563-9387-02bf88a943dc/11/BOXART-16X9/en-US._UR1920,1080_.jpg",
    "liveinfo": "UPCOMING",
    "time_badge": "Tomorrow 6:55 PM",
    "link": "/gp/video/detail/B0DNYTLS76/ref=atv_hm_liv_c_czP1UB_1_111?jic=8%7CEgNhbGw%3D",
    "status": "UPCOMING"
  },
  {
    "display_title": "Marlins at White Sox",
    "title": "Marlins at White Sox",
    "titleID": "B0DYD5SBZH",
    "synopsis": "Watch Marlins at White Sox LIVE from Chicago.",
    "poster": "https://m.media-amazon.com/images/S/le-target-images-prod/amzn1.dv.gti.55341a4d-6be7-4a09-8c07-7b6a4bc93618/113/BOXART-16X9/en-US._UR1920,1080_.png",
    "liveinfo": "UPCOMING",
    "time_badge": "Tomorrow 7:10 PM",
    "link": "/gp/video/detail/B0DYD5SBZH/ref=atv_hm_liv_c_czP1UB_1_112?jic=8%7CEgNhbGw%3D",
    "status": "UPCOMING"
  },
  {
    "display_title": "Red Sox at Royals",
    "title": "Red Sox at Royals",
    "titleID": "B0DRK4PVT1",
    "synopsis": "Watch Red Sox at Royals LIVE from Kansas City.",
    "poster": "https://m.media-amazon.com/images/S/le-target-images-prod/amzn1.dv.gti.5c9d5623-f48a-46d2-bc4d-f92cbf6a7b28/112/BOXART-16X9/en-US._UR1920,1080_.png",
    "liveinfo": "UPCOMING",
    "time_badge": "Tomorrow 7:10 PM",
    "link": "/gp/video/detail/B0DRK4PVT1/ref=atv_hm_liv_c_czP1UB_1_113?jic=8%7CEgNhbGw%3D",
    "status": "UPCOMING"
  },
  {
    "display_title": "Reds at Astros",
    "title": "Reds at Astros",
    "titleID": "B0F643ZB7Q",
    "synopsis": "Watch Reds at Astros LIVE from Houston.",
    "poster": "https://m.media-amazon.com/images/S/le-target-images-prod/amzn1.dv.gti.e45870a6-9da8-45dc-a0a9-ae1becc0f612/118/BOXART-16X9/en-US._UR1920,1080_.png",
    "liveinfo": "UPCOMING",
    "time_badge": "Tomorrow 7:10 PM",
    "link": "/gp/video/detail/B0F643ZB7Q/ref=atv_hm_liv_c_czP1UB_1_114?jic=8%7CEgNhbGw%3D",
    "status": "UPCOMING"
  },
  {
    "display_title": "Giants at Twins",
    "title": "Giants at Twins",
    "titleID": "B0DNW4MYTM",
    "synopsis": "Watch Giants at Twins LIVE from Minneapolis.",
    "poster": "https://m.media-amazon.com/images/S/le-target-images-prod/amzn1.dv.gti.a42007e0-8b5d-4a02-ac35-b5b6053b99bb/115/BOXART-16X9/en-US._UR1920,1080_.png",
    "liveinfo": "UPCOMING",
    "time_badge": "Tomorrow 7:15 PM",
    "link": "/gp/video/detail/B0DNW4MYTM/ref=atv_hm_liv_c_czP1UB_1_115?jic=8%7CEgNhbGw%3D",
    "status": "UPCOMING"
  },
  {
    "display_title": "Cubs at Mets",
    "title": "Cubs at Mets",
    "titleID": "B0DVRQBGVT",
    "synopsis": "Watch Cubs at Mets LIVE from Flushing, Queens.",
    "poster": "https://m.media-amazon.com/images/S/le-target-images-prod/amzn1.dv.gti.b70f5b99-f001-4ffb-b659-5158ceb1242f/113/BOXART-16X9/en-US._UR1920,1080_.png",
    "liveinfo": "UPCOMING",
    "time_badge": "Tomorrow 7:15 PM",
    "link": "/gp/video/detail/B0DVRQBGVT/ref=atv_hm_liv_c_czP1UB_1_116?jic=8%7CEgNhbGw%3D",
    "status": "UPCOMING"
  },
  {
    "display_title": " North Carolina Courage vs. Orlando Pride",
    "title": " North Carolina Courage vs. Orlando Pride",
    "titleID": "B0F4JBJS4Z",
    "synopsis": " Watch North Carolina Courage host Orlando Pride  at First Horizon Stadium at WakeMed Soccer Park broadcasting live from Cary!",
    "poster": "https://m.media-amazon.com/images/S/le-target-images-prod/amzn1.dv.gti.dea04d83-8004-4733-aedc-ca2c2e94597f/9/BOXART-16X9/en-US/1920x1080._UR1920,1080_.png",
    "liveinfo": "UPCOMING",
    "time_badge": "Tomorrow 7:25 PM",
    "link": "/gp/video/detail/B0F4JBJS4Z/ref=atv_hm_liv_c_czP1UB_1_117?jic=8%7CEgNhbGw%3D",
    "status": "UPCOMING"
  },
  {
    "display_title": "New York City FC vs. CF Montréal",
    "title": "New York City FC vs. CF Montréal",
    "titleID": "B0F1G41XX3",
    "synopsis": "Watch New York City FC host CF Montréal  at Yankee Stadium broadcasting live from New York City!",
    "poster": "https://m.media-amazon.com/images/S/le-target-images-prod/amzn1.dv.gti.fac94a13-f881-4f1b-a78c-baab0bdd06a1/46/BOXART-16X9/en-US/1920x1080._UR1920,1080_.png",
    "liveinfo": "UPCOMING",
    "time_badge": "Tomorrow 7:25 PM",
    "link": "/gp/video/detail/B0F1G41XX3/ref=atv_hm_liv_c_czP1UB_1_118?jic=8%7CEgNhbGw%3D",
    "status": "UPCOMING"
  },
  {
    "display_title": "FC Cincinnati vs. Austin FC",
    "title": "FC Cincinnati vs. Austin FC",
    "titleID": "B0BCSSR1BD",
    "synopsis": "Watch FC Cincy host Austin",
    "poster": "https://m.media-amazon.com/images/S/le-target-images-prod/amzn1.dv.gti.4c0b1500-abce-4ed3-9337-332891508fbe/2/BOXART-16X9/en-US/1920x1080._UR1920,1080_.png",
    "liveinfo": "UPCOMING",
    "time_badge": "Tomorrow 7:30 PM",
    "link": "/gp/video/detail/B0BCSSR1BD/ref=atv_hm_liv_c_czP1UB_1_119?jic=8%7CEgNhbGw%3D",
    "status": "UPCOMING"
  },
  {
    "display_title": "New York Red Bulls vs. LA Galaxy",
    "title": "New York Red Bulls vs. LA Galaxy",
    "titleID": "B0DTJ26VPS",
    "synopsis": "Watch the Red Bulls host the Galaxy",
    "poster": "https://m.media-amazon.com/images/S/le-target-images-prod/amzn1.dv.gti.62e8f4c8-89b3-4ac0-915e-8c57f11efb50/3/BOXART-16X9/en-US/1920x1080._UR1920,1080_.png",
    "liveinfo": "UPCOMING",
    "time_badge": "Tomorrow 7:30 PM",
    "link": "/gp/video/detail/B0DTJ26VPS/ref=atv_hm_liv_c_czP1UB_1_120?jic=8%7CEgNhbGw%3D",
    "status": "UPCOMING"
  },
  {
    "display_title": "SEC Tournament: Texas A&M vs. Oklahoma",
    "title": "SEC Tournament: Texas A&M vs. Oklahoma",
    "titleID": "B0DTLHT5FS",
    "synopsis": "Championship.",
    "poster": "https://m.media-amazon.com/images/S/le-target-images-prod/amzn1.dv.gti.8916559e-64eb-4172-a62e-9b91ec757803/3/BOXART-16X9/en-US._UR1920,1080_.jpg",
    "liveinfo": "UPCOMING",
    "time_badge": "Tomorrow 4:55 PM",
    "link": "/gp/video/detail/B0DTLHT5FS/ref=atv_hm_liv_c_czP1UB_1_101?jic=8%7CEgNhbGw%3D",
    "status": "UPCOMING"
  },
  {
    "display_title": "Vanderbilt at Tennessee",
    "title": "Vanderbilt at Tennessee",
    "titleID": "B0DC5P1RBM",
    "synopsis": "From Lindsey Nelson Stadium in Knoxville, Tenn.",
    "poster": "https://m.media-amazon.com/images/S/le-target-images-prod/amzn1.dv.gti.9a00fc68-c334-4490-bed8-6898465abc53/1/BOXART-16X9/en-US._UR1920,1080_.jpg",
    "liveinfo": "UPCOMING",
    "time_badge": "Tomorrow 4:55 PM",
    "link": "/gp/video/detail/B0DC5P1RBM/ref=atv_hm_liv_c_czP1UB_1_102?jic=8%7CEgNhbGw%3D",
    "status": "UPCOMING"
  },
  {
    "display_title": "Cavalry FC at HFX Wanderers FC",
    "title": "Cavalry FC at HFX Wanderers FC",
    "titleID": "B0F4PDGN9W",
    "synopsis": "From Wanderers Grounds in Halifax, Nova Scotia.",
    "poster": "https://m.media-amazon.com/images/S/le-target-images-prod/amzn1.dv.gti.73abaf6f-3fa0-4e1a-9da9-d4ca905809a5/1/BOXART-16X9/en-US._UR1920,1080_.jpg",
    "liveinfo": "UPCOMING",
    "time_badge": "Tomorrow 5:25 PM",
    "link": "/gp/video/detail/B0F4PDGN9W/ref=atv_hm_liv_c_czP1UB_1_103?jic=8%7CEgNhbGw%3D",
    "status": "UPCOMING"
  },
  {
    "display_title": "Brooklyn vs. Spokane Zephyr",
    "title": "Brooklyn vs. Spokane Zephyr",
    "titleID": "B0F13GRQG2",
    "synopsis": "Watch Brooklyn take on Spokane Zephyr in the USL Super League.",
    "poster": "https://m.media-amazon.com/images/S/le-target-images-prod/amzn1.dv.gti.80ec0bc4-872a-4195-a97d-0a30766dd76a/2/BOXART-16X9/en-US._UR1920,1080_.png",
    "liveinfo": "UPCOMING",
    "time_badge": "Tomorrow 5:49 PM",
    "link": "/gp/video/detail/B0F13GRQG2/ref=atv_hm_liv_c_czP1UB_1_104?jic=8%7CEgNhbGw%3D",
    "status": "UPCOMING"
  },
  {
    "display_title": "Capitals at Hurricanes",
    "title": "Capitals at Hurricanes",
    "titleID": "B0DT7LNMY4",
    "synopsis": "Stanley Cup Playoffs: Watch the Washington Capitals and the Carolina Hurricanes face off at Lenovo Center broadcasting live from Raleigh!",
    "poster": "https://m.media-amazon.com/images/S/le-target-images-prod/amzn1.dv.gti.6dfe90b9-0a2d-4294-9588-4ad4de4707d5/86/BOXART-16X9/en-US/1920x1080._UR1920,1080_.png",
    "liveinfo": "UPCOMING",
    "time_badge": "Tomorrow 5:55 PM",
    "link": "/gp/video/detail/B0DT7LNMY4/ref=atv_hm_liv_c_czP1UB_1_105?jic=8%7CEgNhbGw%3D",
    "status": "UPCOMING"
  },
  {
    "display_title": "Phillies at Guardians",
    "title": "Phillies at Guardians",
    "titleID": "B0DTCDR8G9",
    "synopsis": "Watch Phillies at Guardians LIVE from Cleveland.",
    "poster": "https://m.media-amazon.com/images/S/le-target-images-prod/amzn1.dv.gti.68446296-28da-4353-8ff1-e51df5a690ba/113/BOXART-16X9/en-US._UR1920,1080_.png",
    "liveinfo": "UPCOMING",
    "time_badge": "Tomorrow 6:10 PM",
    "link": "/gp/video/detail/B0DTCDR8G9/ref=atv_hm_liv_c_czP1UB_1_106?jic=8%7CEgNhbGw%3D",
    "status": "UPCOMING"
  },
  {
    "display_title": "Rangers at Tigers",
    "title": "Rangers at Tigers",
    "titleID": "B0F513WPLH",
    "synopsis": "Watch Rangers at Tigers LIVE from Detroit.",
    "poster": "https://m.media-amazon.com/images/S/le-target-images-prod/amzn1.dv.gti.6d3b1025-35a5-40f2-930f-389f957f7958/112/BOXART-16X9/en-US._UR1920,1080_.png",
    "liveinfo": "UPCOMING",
    "time_badge": "Tomorrow 6:10 PM",
    "link": "/gp/video/detail/B0F513WPLH/ref=atv_hm_liv_c_czP1UB_1_107?jic=8%7CEgNhbGw%3D",
    "status": "UPCOMING"
  },
  {
    "display_title": "MLS Countdown",
    "title": "MLS Countdown",
    "titleID": "B0F25CF7K2",
    "synopsis": "Get set for kickoff with match breakdowns, expert insight, and more.",
    "poster": "https://m.media-amazon.com/images/S/le-target-images-prod/amzn1.dv.gti.16239456-363f-4b2b-b654-e706eb6acafb/1/BOXART-16X9/en-US._UR1920,1080_.jpeg",
    "liveinfo": "UPCOMING",
    "time_badge": "Tomorrow 6:30 PM",
    "link": "/gp/video/detail/B0F25CF7K2/ref=atv_hm_liv_c_czP1UB_1_108?jic=8%7CEgNhbGw%3D",
    "status": "UPCOMING"
  },
  {
    "display_title": "MLS La Previa",
    "title": "MLS La Previa",
    "titleID": "B0F3VMDL2Y",
    "synopsis": "Everything you need to get set for matchday. (En español)",
    "poster": "https://m.media-amazon.com/images/S/le-target-images-prod/amzn1.dv.gti.7ec33d72-2252-46b5-b91c-aa7361e7912a/1/BOXART-16X9/en-US._UR1920,1080_.jpeg",
    "liveinfo": "UPCOMING",
    "time_badge": "Tomorrow 6:30 PM",
    "link": "/gp/video/detail/B0F3VMDL2Y/ref=atv_hm_liv_c_czP1UB_1_109?jic=8%7CEgNhbGw%3D",
    "status": "UPCOMING"
  },
  {
    "display_title": "Avant-match soccer: CF Montréal",
    "title": "Avant-match soccer: CF Montréal",
    "titleID": "B0F2NDPXS4",
    "synopsis": "Un avant-goût du prochain match du CF Montréal.",
    "poster": "https://m.media-amazon.com/images/S/le-target-images-prod/amzn1.dv.gti.7060b788-f66d-48ba-816a-7f1df0f47643/6/BOXART-16X9/fr-CA._UR1920,1080_.jpg",
    "liveinfo": "UPCOMING",
    "time_badge": "Tomorrow 6:55 PM",
    "link": "/gp/video/detail/B0F2NDPXS4/ref=atv_hm_liv_c_czP1UB_1_110?jic=8%7CEgNhbGw%3D",
    "status": "UPCOMING"
  },
  {
    "display_title": "PTT Stockton Men - Day 6",
    "title": "PTT Stockton Men - Day 6",
    "titleID": "B0DHW3F2TH",
    "synopsis": "PTT Stockton Men - Day 6",
    "poster": "https://m.media-amazon.com/images/S/le-target-images-prod/amzn1.dv.gti.ad0d63c8-6a92-4003-a85e-938d44b64a95/1/BOXART-16X9/en-US._UR1920,1080_.png",
    "liveinfo": "UPCOMING",
    "time_badge": "Tomorrow 11:55 AM",
    "link": "/gp/video/detail/B0DHW3F2TH/ref=atv_hm_liv_c_czP1UB_1_71?jic=8%7CEgNhbGw%3D",
    "status": "UPCOMING"
  },
  {
    "display_title": "AFC Bournemouth vs. Aston Villa FC",
    "title": "AFC Bournemouth vs. Aston Villa FC",
    "titleID": "B0DZQ64LXQ",
    "synopsis": "Watch AFC Bournemouth take on Aston Villa FC",
    "poster": "https://m.media-amazon.com/images/S/le-target-images-prod/amzn1.dv.gti.462e4f0a-dda6-45d7-85d9-f8395b82dae1/4/BOXART-16X9/en-US._UR1920,1080_.jpg",
    "liveinfo": "UPCOMING",
    "time_badge": "Tomorrow 12:10 PM",
    "link": "/gp/video/detail/B0DZQ64LXQ/ref=atv_hm_liv_c_czP1UB_1_72?jic=8%7CEgNhbGw%3D",
    "status": "UPCOMING"
  },
  {
    "display_title": "FC Bayern München vs. Borussia VfL Mönchengladbach",
    "title": "FC Bayern München vs. Borussia VfL Mönchengladbach",
    "titleID": "B0F6KM778H",
    "synopsis": "Watch FC Bayern München take on Borussia VfL Mönchengladbach",
    "poster": "https://m.media-amazon.com/images/S/le-target-images-prod/amzn1.dv.gti.309a942d-f12b-4f5c-9c7a-f3494dcc3b92/3/BOXART-16X9/en-US._UR1920,1080_.png",
    "liveinfo": "UPCOMING",
    "time_badge": "Tomorrow 12:12 PM",
    "link": "/gp/video/detail/B0F6KM778H/ref=atv_hm_liv_c_czP1UB_1_73?jic=8%7CEgNhbGw%3D",
    "status": "UPCOMING"
  },
  {
    "display_title": "Girona FC vs. Villarreal CF",
    "title": "Girona FC vs. Villarreal CF",
    "titleID": "B0F47NGWKF",
    "synopsis": "Watch Girona FC take on Villarreal CF",
    "poster": "https://m.media-amazon.com/images/S/le-target-images-prod/amzn1.dv.gti.6a973e52-d11c-4908-9080-931b3e798c93/22/BOXART-16X9/en-US._UR1920,1080_.jpg",
    "liveinfo": "UPCOMING",
    "time_badge": "Tomorrow 12:19 PM",
    "link": "/gp/video/detail/B0F47NGWKF/ref=atv_hm_liv_c_czP1UB_1_74?jic=8%7CEgNhbGw%3D",
    "status": "UPCOMING"
  },
  {
    "display_title": "Real Club Deportivo Mallorca vs. Real Valladolid CF",
    "title": "Real Club Deportivo Mallorca vs. Real Valladolid CF",
    "titleID": "B0F4QWF48Q",
    "synopsis": "Watch Real Club Deportivo Mallorca take on Real Valladolid CF",
    "poster": "https://m.media-amazon.com/images/S/le-target-images-prod/amzn1.dv.gti.9dbabc20-b052-426d-b78d-2aa12571b6a1/6/BOXART-16X9/en-US._UR1920,1080_.jpg",
    "liveinfo": "UPCOMING",
    "time_badge": "Tomorrow 12:19 PM",
    "link": "/gp/video/detail/B0F4QWF48Q/ref=atv_hm_liv_c_czP1UB_1_75?jic=8%7CEgNhbGw%3D",
    "status": "UPCOMING"
  },
  {
    "display_title": "Michigan Panthers at Arlington Renegades",
    "title": "Michigan Panthers at Arlington Renegades",
    "titleID": "B0DXXFRJ2Y",
    "synopsis": "The Renegades host the Panthers",
    "poster": "https://m.media-amazon.com/images/S/le-target-images-prod/amzn1.dv.gti.34456517-501b-4460-b1d5-ddab2d80b51e/4/BOXART-16X9/en-US._UR1920,1080_.jpg",
    "liveinfo": "UPCOMING",
    "time_badge": "Tomorrow 12:55 PM",
    "link": "/gp/video/detail/B0DXXFRJ2Y/ref=atv_hm_liv_c_czP1UB_1_76?jic=8%7CEgNhbGw%3D",
    "status": "UPCOMING"
  },
  {
    "display_title": "Truist Championship, Third Round: Featured Holes",
    "title": "Truist Championship, Third Round: Featured Holes",
    "titleID": "B0DSCMYGSH",
    "synopsis": "From The Philadelphia Cricket Club (Wissahickon Course) in Philadelphia.",
    "poster": "https://m.media-amazon.com/images/S/le-target-images-prod/amzn1.dv.gti.5b54f472-bcc4-4849-bd25-8f7f861332b9/2/BOXART-16X9/en-US._UR1920,1080_.jpg",
    "liveinfo": "UPCOMING",
    "time_badge": "Tomorrow 12:55 PM",
    "link": "/gp/video/detail/B0DSCMYGSH/ref=atv_hm_liv_c_czP1UB_1_77?jic=8%7CEgNhbGw%3D",
    "status": "UPCOMING"
  },
  {
    "display_title": "Denmark vs. Switzerland",
    "title": "Denmark vs. Switzerland",
    "titleID": "B0DMTP18SP",
    "synopsis": "Group B.",
    "poster": "https://m.media-amazon.com/images/S/le-target-images-prod/amzn1.dv.gti.6b60ce99-13b9-4800-99a2-1402936bf9ce/13/BOXART-16X9/en-US._UR1920,1080_.jpg",
    "liveinfo": "UPCOMING",
    "time_badge": "Tomorrow 1:55 PM",
    "link": "/gp/video/detail/B0DMTP18SP/ref=atv_hm_liv_c_czP1UB_1_78?jic=8%7CEgNhbGw%3D",
    "status": "UPCOMING"
  },
  {
    "display_title": "France vs. Latvia",
    "title": "France vs. Latvia",
    "titleID": "B0F39PXDZ3",
    "synopsis": "Group A.",
    "poster": "https://m.media-amazon.com/images/S/le-target-images-prod/amzn1.dv.gti.ede6f71d-7f52-4b9a-970d-02715f573cfd/8/BOXART-16X9/en-US._UR1920,1080_.jpg",
    "liveinfo": "UPCOMING",
    "time_badge": "Tomorrow 1:55 PM",
    "link": "/gp/video/detail/B0F39PXDZ3/ref=atv_hm_liv_c_czP1UB_1_79?jic=8%7CEgNhbGw%3D",
    "status": "UPCOMING"
  },
  {
    "display_title": "Cacace vs. Wood",
    "title": "Cacace vs. Wood",
    "titleID": "B0F5PWGGJS",
    "synopsis": "Leigh Wood (28-3) enjoys his maiden outing at super featherweight, taking on Irish champion Anthony Cacace (23-1). With Wood having been inactive since late 2023, can he mark his return with a huge victory against one of the division's best?",
    "poster": "https://m.media-amazon.com/images/S/le-target-images-prod/amzn1.dv.gti.86333a4b-698e-422d-8901-2d0ad7df31b3/3/BOXART-16X9/en-US._UR1920,1080_.jpeg",
    "liveinfo": "UPCOMING",
    "time_badge": "Tomorrow 1:57 PM",
    "link": "/gp/video/detail/B0F5PWGGJS/ref=atv_hm_liv_c_czP1UB_1_80?jic=8%7CEgNhbGw%3D",
    "status": "UPCOMING"
  },
  {
    "display_title": "Juventus vs. Inter Milan",
    "title": "Juventus vs. Inter Milan",
    "titleID": "B0DXM8Q6M3",
    "synopsis": "The women's Serie A action continues, as the top players in Italy do battle.",
    "poster": "https://m.media-amazon.com/images/S/le-target-images-prod/amzn1.dv.gti.b044fe9e-0093-4fce-bc7f-a5addd0cd1e3/1/BOXART-16X9/en-US._UR1920,1080_.png",
    "liveinfo": "UPCOMING",
    "time_badge": "Tomorrow 2:19 PM",
    "link": "/gp/video/detail/B0DXM8Q6M3/ref=atv_hm_liv_c_czP1UB_1_81?jic=8%7CEgNhbGw%3D",
    "status": "UPCOMING"
  },
  {
    "display_title": "Napoli vs. Trento",
    "title": "Napoli vs. Trento",
    "titleID": "B0DC4BP38Y",
    "synopsis": "Watch basketball from Italy as Napoli takes on Trento in the Lega Basket Serie A.",
    "poster": "https://m.media-amazon.com/images/S/le-target-images-prod/amzn1.dv.gti.dce7d5ab-9230-461b-89b1-05461cb8e8c8/1/BOXART-16X9/en-US._UR1920,1080_.png",
    "liveinfo": "UPCOMING",
    "time_badge": "Tomorrow 2:20 PM",
    "link": "/gp/video/detail/B0DC4BP38Y/ref=atv_hm_liv_c_czP1UB_1_82?jic=8%7CEgNhbGw%3D",
    "status": "UPCOMING"
  },
  {
    "display_title": "Club Atlético de Madrid vs. Sociedad",
    "title": "Club Atlético de Madrid vs. Sociedad",
    "titleID": "B0F5FVP9FB",
    "synopsis": "Watch Club Atlético de Madrid take on Sociedad",
    "poster": "https://m.media-amazon.com/images/S/le-target-images-prod/amzn1.dv.gti.0daf9a72-0f4e-47fa-adab-f7492f6a3803/36/BOXART-16X9/en-US._UR1920,1080_.jpg",
    "liveinfo": "UPCOMING",
    "time_badge": "Tomorrow 2:25 PM",
    "link": "/gp/video/detail/B0F5FVP9FB/ref=atv_hm_liv_c_czP1UB_1_83?jic=8%7CEgNhbGw%3D",
    "status": "UPCOMING"
  },
  {
    "display_title": "Hamburg vs. Ulm",
    "title": "Hamburg vs. Ulm",
    "titleID": "B0F7H9T3WV",
    "synopsis": "Watch Hamburg take on Ulm in 2.Bundesliga.",
    "poster": "https://m.media-amazon.com/images/S/le-target-images-prod/amzn1.dv.gti.419c5054-6956-432d-bc04-fc1432446716/1/BOXART-16X9/en-US._UR1920,1080_.png",
    "liveinfo": "UPCOMING",
    "time_badge": "Tomorrow 2:25 PM",
    "link": "/gp/video/detail/B0F7H9T3WV/ref=atv_hm_liv_c_czP1UB_1_84?jic=8%7CEgNhbGw%3D",
    "status": "UPCOMING"
  },
  {
    "display_title": "ACC Tournament: Clemson vs. Florida State",
    "title": "ACC Tournament: Clemson vs. Florida State",
    "titleID": "B0F27Q34SM",
    "synopsis": "Championship.",
    "poster": "https://m.media-amazon.com/images/S/le-target-images-prod/amzn1.dv.gti.44a878f4-00cc-46eb-aeaf-3bb88f910e04/5/BOXART-16X9/en-US._UR1920,1080_.jpg",
    "liveinfo": "UPCOMING",
    "time_badge": "Tomorrow 2:25 PM",
    "link": "/gp/video/detail/B0F27Q34SM/ref=atv_hm_liv_c_czP1UB_1_85?jic=8%7CEgNhbGw%3D",
    "status": "UPCOMING"
  },
  {
    "display_title": "Sun Belt Tournament: James Madison vs. Coastal Carolina",
    "title": "Sun Belt Tournament: James Madison vs. Coastal Carolina",
    "titleID": "B0DQCC9399",
    "synopsis": "Championship.",
    "poster": "https://m.media-amazon.com/images/S/le-target-images-prod/amzn1.dv.gti.490bc137-050f-4eb8-958e-42ef830635f9/4/BOXART-16X9/en-US._UR1920,1080_.jpg",
    "liveinfo": "UPCOMING",
    "time_badge": "Tomorrow 2:25 PM",
    "link": "/gp/video/detail/B0DQCC9399/ref=atv_hm_liv_c_czP1UB_1_86?jic=8%7CEgNhbGw%3D",
    "status": "UPCOMING"
  },
  {
    "display_title": "Empoli FC vs. Parma Calcio 1913",
    "title": "Empoli FC vs. Parma Calcio 1913",
    "titleID": "B0DYQRVP2M",
    "synopsis": "Watch Empoli FC take on Parma Calcio 1913",
    "poster": "https://m.media-amazon.com/images/S/le-target-images-prod/amzn1.dv.gti.afd96aff-e220-4c76-93d8-6463cf2587c7/4/BOXART-16X9/en-US._UR1920,1080_.jpg",
    "liveinfo": "UPCOMING",
    "time_badge": "Tomorrow 2:30 PM",
    "link": "/gp/video/detail/B0DYQRVP2M/ref=atv_hm_liv_c_czP1UB_1_87?jic=8%7CEgNhbGw%3D",
    "status": "UPCOMING"
  },
  {
    "display_title": "Anderlecht vs. Union Saint-Gilloise",
    "title": "Anderlecht vs. Union Saint-Gilloise",
    "titleID": "B0DSLY8Y6B",
    "synopsis": "Catch all the latest action from the top flight of Belgian soccer, as Anderlecht faces Union Saint-Gilloise in the Belgian Pro League.",
    "poster": "https://m.media-amazon.com/images/S/le-target-images-prod/amzn1.dv.gti.a56913be-b4c5-4989-9a1b-dc78505002af/2/BOXART-16X9/en-US._UR1920,1080_.png",
    "liveinfo": "UPCOMING",
    "time_badge": "Tomorrow 2:32 PM",
    "link": "/gp/video/detail/B0DSLY8Y6B/ref=atv_hm_liv_c_czP1UB_1_88?jic=8%7CEgNhbGw%3D",
    "status": "UPCOMING"
  },
  {
    "display_title": "Notts County vs. AFC Wimbledon",
    "title": "Notts County vs. AFC Wimbledon",
    "titleID": "B0F5PNGTRN",
    "synopsis": "Catch all the latest League Two action live on DAZN.",
    "poster": "https://m.media-amazon.com/images/S/le-target-images-prod/amzn1.dv.gti.6d9ba0fd-bcb3-4c21-80cc-89e46a3716ab/1/BOXART-16X9/en-US._UR1920,1080_.png",
    "liveinfo": "UPCOMING",
    "time_badge": "Tomorrow 2:44 PM",
    "link": "/gp/video/detail/B0F5PNGTRN/ref=atv_hm_liv_c_czP1UB_1_89?jic=8%7CEgNhbGw%3D",
    "status": "UPCOMING"
  },
  {
    "display_title": "PGA Tour",
    "title": "PGA Tour",
    "titleID": "B0DK3X7J6P",
    "synopsis": "From The Philadelphia Cricket Club (Wissahickon Course) in Philadelphia.",
    "poster": "https://m.media-amazon.com/images/S/le-target-images-prod/amzn1.dv.gti.68889584-4dcd-4f95-ade1-6d4ff4e45422/16/BOXART-16X9/en-US._UR1920,1080_.jpg",
    "liveinfo": "UPCOMING",
    "time_badge": "Tomorrow 2:55 PM",
    "link": "/gp/video/detail/B0DK3X7J6P/ref=atv_hm_liv_c_czP1UB_1_90?jic=8%7CEgNhbGw%3D",
    "status": "UPCOMING"
  },
  {
    "display_title": "Cacace vs. Wood: Prelims",
    "title": "Cacace vs. Wood: Prelims",
    "titleID": "B0F4P18X13",
    "synopsis": "Watch the biggest names and the best fights on DAZN, the global home of boxing.\n",
    "poster": "https://m.media-amazon.com/images/S/le-target-images-prod/amzn1.dv.gti.02e96853-8e98-415b-9e00-d80e5748ece5/5/BOXART-16X9/en-US._UR1920,1080_.jpeg",
    "liveinfo": "UPCOMING",
    "time_badge": "Tomorrow 9:57 AM",
    "link": "/gp/video/detail/B0F4P18X13/ref=atv_hm_liv_c_czP1UB_1_61?jic=8%7CEgNhbGw%3D",
    "status": "UPCOMING"
  },
  {
    "display_title": "Real Club Celta de Vigo vs. Sevilla FC",
    "title": "Real Club Celta de Vigo vs. Sevilla FC",
    "titleID": "B0F66P11N9",
    "synopsis": "Watch Real Club Celta de Vigo take on Sevilla FC",
    "poster": "https://m.media-amazon.com/images/S/le-target-images-prod/amzn1.dv.gti.25f223eb-2b84-4e2d-b88e-a853879cd418/26/BOXART-16X9/en-US._UR1920,1080_.jpg",
    "liveinfo": "UPCOMING",
    "time_badge": "Tomorrow 10:04 AM",
    "link": "/gp/video/detail/B0F66P11N9/ref=atv_hm_liv_c_czP1UB_1_62?jic=8%7CEgNhbGw%3D",
    "status": "UPCOMING"
  },
  {
    "display_title": "Red Bull Rookies Cup - Day 1 Le Mans",
    "title": "Red Bull Rookies Cup - Day 1 Le Mans",
    "titleID": "B0DT4Q9M98",
    "synopsis": "Watch the latest action from Red Bull TV.",
    "poster": "https://m.media-amazon.com/images/S/le-target-images-prod/amzn1.dv.gti.fb2d349c-7f2c-4eb9-b920-0f78537b57eb/3/BOXART-16X9/en-US._UR1920,1080_.png",
    "liveinfo": "UPCOMING",
    "time_badge": "Tomorrow 10:50 AM",
    "link": "/gp/video/detail/B0DT4Q9M98/ref=atv_hm_liv_c_czP1UB_1_63?jic=8%7CEgNhbGw%3D",
    "status": "UPCOMING"
  },
  {
    "display_title": "Pakistan Super League 2025 - 29th Match - Islamabad United vs Karachi Kings",
    "title": "Pakistan Super League 2025 - 29th Match - Islamabad United vs Karachi Kings",
    "titleID": "B0F24BFML1",
    "synopsis": "Pakistan Super League 2025 - 29th Match - Islamabad United vs Karachi Kings",
    "poster": "https://m.media-amazon.com/images/S/le-target-images-prod/amzn1.dv.gti.be85ef94-af48-41ff-a390-062871ed4c3e/4/BOXART-16X9/en-US._UR1920,1080_.jpeg",
    "liveinfo": "UPCOMING",
    "time_badge": "Tomorrow 10:55 AM",
    "link": "/gp/video/detail/B0F24BFML1/ref=atv_hm_liv_c_czP1UB_1_64?jic=8%7CEgNhbGw%3D",
    "status": "UPCOMING"
  },
  {
    "display_title": "Semifinal: Portugal vs. Brazil",
    "title": "Semifinal: Portugal vs. Brazil",
    "titleID": "B0BCH3LTQW",
    "synopsis": "From Paradise Arena, in Victoria, Seychelles.",
    "poster": "https://m.media-amazon.com/images/S/le-target-images-prod/amzn1.dv.gti.531efc50-436e-4e14-8811-b51b8b499bf9/87/BOXART-16X9/en-US._UR1920,1080_.jpg",
    "liveinfo": "UPCOMING",
    "time_badge": "Tomorrow 11:13 AM",
    "link": "/gp/video/detail/B0BCH3LTQW/ref=atv_hm_liv_c_czP1UB_1_65?jic=8%7CEgNhbGw%3D",
    "status": "UPCOMING"
  },
  {
    "display_title": "SS Lazio vs. Juventus FC",
    "title": "SS Lazio vs. Juventus FC",
    "titleID": "B0CVXDQ665",
    "synopsis": "Watch SS Lazio take on Juventus FC",
    "poster": "https://m.media-amazon.com/images/S/le-target-images-prod/amzn1.dv.gti.0614c985-91b5-4030-9a98-b70b077ec706/6/BOXART-16X9/en-US._UR1920,1080_.jpg",
    "liveinfo": "UPCOMING",
    "time_badge": "Tomorrow 11:45 AM",
    "link": "/gp/video/detail/B0CVXDQ665/ref=atv_hm_liv_c_czP1UB_1_66?jic=8%7CEgNhbGw%3D",
    "status": "UPCOMING"
  },
  {
    "display_title": "KOK Fight Night - Baar, Switzerland",
    "title": "KOK Fight Night - Baar, Switzerland",
    "titleID": "B0F6T4FRZ1",
    "synopsis": "Watch all the latest King of Kings action as the stars enter the cage live in Baar.",
    "poster": "https://m.media-amazon.com/images/S/le-target-images-prod/amzn1.dv.gti.4f231439-acae-4d33-b046-489cf4ba2baf/2/BOXART-16X9/en-US._UR1920,1080_.jpeg",
    "liveinfo": "UPCOMING",
    "time_badge": "Tomorrow 11:54 AM",
    "link": "/gp/video/detail/B0F6T4FRZ1/ref=atv_hm_liv_c_czP1UB_1_67?jic=8%7CEgNhbGw%3D",
    "status": "UPCOMING"
  },
  {
    "display_title": "AAC Tournament: North Texas vs. South Florida",
    "title": "AAC Tournament: North Texas vs. South Florida",
    "titleID": "B0F69BKHGW",
    "synopsis": "Championship.",
    "poster": "https://m.media-amazon.com/images/S/le-target-images-prod/amzn1.dv.gti.3bd27ff5-389d-42a5-99f4-8466fdacf41e/3/BOXART-16X9/en-US._UR1920,1080_.jpg",
    "liveinfo": "UPCOMING",
    "time_badge": "Tomorrow 11:55 AM",
    "link": "/gp/video/detail/B0F69BKHGW/ref=atv_hm_liv_c_czP1UB_1_68?jic=8%7CEgNhbGw%3D",
    "status": "UPCOMING"
  },
  {
    "display_title": "PTT Stockton Women - Day 6",
    "title": "PTT Stockton Women - Day 6",
    "titleID": "B0DT2M6HP3",
    "synopsis": "PTT Stockton Women - Day 6",
    "poster": "https://m.media-amazon.com/images/S/le-target-images-prod/amzn1.dv.gti.636095eb-8924-41fb-b752-f4fe92e5fe8a/1/BOXART-16X9/en-US._UR1920,1080_.png",
    "liveinfo": "UPCOMING",
    "time_badge": "Tomorrow 11:55 AM",
    "link": "/gp/video/detail/B0DT2M6HP3/ref=atv_hm_liv_c_czP1UB_1_69?jic=8%7CEgNhbGw%3D",
    "status": "UPCOMING"
  },
  {
    "display_title": "Big 12 Tournament: Arizona vs. Texas Tech",
    "title": "Big 12 Tournament: Arizona vs. Texas Tech",
    "titleID": "B0DWVCVFHM",
    "synopsis": "Championship.",
    "poster": "https://m.media-amazon.com/images/S/le-target-images-prod/amzn1.dv.gti.7399c947-2d45-4f6e-8c2c-7d9f49910f3a/5/BOXART-16X9/en-US._UR1920,1080_.jpg",
    "liveinfo": "UPCOMING",
    "time_badge": "Tomorrow 11:55 AM",
    "link": "/gp/video/detail/B0DWVCVFHM/ref=atv_hm_liv_c_czP1UB_1_70?jic=8%7CEgNhbGw%3D",
    "status": "UPCOMING"
  },
  {
    "display_title": "Truist Championship, Third Round: Main Feed",
    "title": "Truist Championship, Third Round: Main Feed",
    "titleID": "B0DWKW4DKN",
    "synopsis": "From The Philadelphia Cricket Club (Wissahickon Course) in Philadelphia.",
    "poster": "https://m.media-amazon.com/images/S/le-target-images-prod/amzn1.dv.gti.30a13ea7-c8a1-4681-a67c-66e6e610a09a/2/BOXART-16X9/en-US._UR1920,1080_.jpg",
    "liveinfo": "UPCOMING",
    "time_badge": "Tomorrow 7:55 AM",
    "link": "/gp/video/detail/B0DWKW4DKN/ref=atv_hm_liv_c_czP1UB_1_41?jic=8%7CEgNhbGw%3D",
    "status": "UPCOMING"
  },
  {
    "display_title": "RWS: Yothin vs. Chaila",
    "title": "RWS: Yothin vs. Chaila",
    "titleID": "B0D3WNTQCK",
    "synopsis": "The Rajadamnern Stadium plays host to the latest round of RWS action.",
    "poster": "https://m.media-amazon.com/images/S/le-target-images-prod/amzn1.dv.gti.b0b9e134-5341-4f40-aed5-df7b1ac02c56/4/BOXART-16X9/en-US._UR1920,1080_.png",
    "liveinfo": "UPCOMING",
    "time_badge": "Tomorrow 8:00 AM",
    "link": "/gp/video/detail/B0D3WNTQCK/ref=atv_hm_liv_c_czP1UB_1_42?jic=8%7CEgNhbGw%3D",
    "status": "UPCOMING"
  },
  {
    "display_title": "Truist Championship, Third Round: Featured Groups",
    "title": "Truist Championship, Third Round: Featured Groups",
    "titleID": "B0F4DT12YY",
    "synopsis": "From The Philadelphia Cricket Club (Wissahickon Course) in Philadelphia.",
    "poster": "https://m.media-amazon.com/images/S/le-target-images-prod/amzn1.dv.gti.d4eef099-7bb8-4004-b891-088d37eb63d6/2/BOXART-16X9/en-US._UR1920,1080_.jpg",
    "liveinfo": "UPCOMING",
    "time_badge": "Tomorrow 8:40 AM",
    "link": "/gp/video/detail/B0F4DT12YY/ref=atv_hm_liv_c_czP1UB_1_43?jic=8%7CEgNhbGw%3D",
    "status": "UPCOMING"
  },
  {
    "display_title": "Calcio Como 1907 vs. Cagliari Calcio",
    "title": "Calcio Como 1907 vs. Cagliari Calcio",
    "titleID": "B0F5HL1DSL",
    "synopsis": "Watch Calcio Como 1907 take on Cagliari Calcio",
    "poster": "https://m.media-amazon.com/images/S/le-target-images-prod/amzn1.dv.gti.c4ed65e1-1ad8-422d-a508-ff7fccb49703/5/BOXART-16X9/en-US._UR1920,1080_.jpg",
    "liveinfo": "UPCOMING",
    "time_badge": "Tomorrow 8:45 AM",
    "link": "/gp/video/detail/B0F5HL1DSL/ref=atv_hm_liv_c_czP1UB_1_44?jic=8%7CEgNhbGw%3D",
    "status": "UPCOMING"
  },
  {
    "display_title": "Fiorentina vs. Roma",
    "title": "Fiorentina vs. Roma",
    "titleID": "B0DT155P18",
    "synopsis": "The women's Serie A action continues, as the top players in Italy do battle.",
    "poster": "https://m.media-amazon.com/images/S/le-target-images-prod/amzn1.dv.gti.5cdd247b-4f78-477a-bbf9-07e0e3bcafc6/1/BOXART-16X9/en-US._UR1920,1080_.png",
    "liveinfo": "UPCOMING",
    "time_badge": "Tomorrow 8:49 AM",
    "link": "/gp/video/detail/B0DT155P18/ref=atv_hm_liv_c_czP1UB_1_45?jic=8%7CEgNhbGw%3D",
    "status": "UPCOMING"
  },
  {
    "display_title": "Truist Championship, Third Round: Marquee Group",
    "title": "Truist Championship, Third Round: Marquee Group",
    "titleID": "B0F27XPGQB",
    "synopsis": "From The Philadelphia Cricket Club (Wissahickon Course) in Philadelphia.",
    "poster": "https://m.media-amazon.com/images/S/le-target-images-prod/amzn1.dv.gti.6325ec07-d09b-43a9-a448-4a38dcfb7520/2/BOXART-16X9/en-US._UR1920,1080_.jpg",
    "liveinfo": "UPCOMING",
    "time_badge": "Tomorrow 8:55 AM",
    "link": "/gp/video/detail/B0F27XPGQB/ref=atv_hm_liv_c_czP1UB_1_46?jic=8%7CEgNhbGw%3D",
    "status": "UPCOMING"
  },
  {
    "display_title": "FC Union Berlin vs. 1. FC Heidenheim 1846",
    "title": "FC Union Berlin vs. 1. FC Heidenheim 1846",
    "titleID": "B0DDQ6NF7C",
    "synopsis": "Watch FC Union Berlin take on 1. FC Heidenheim 1846",
    "poster": "https://m.media-amazon.com/images/S/le-target-images-prod/amzn1.dv.gti.39b9b220-9e6e-40c1-a268-31d6777233eb/1/BOXART-16X9/en-US._UR1920,1080_.png",
    "liveinfo": "UPCOMING",
    "time_badge": "Tomorrow 9:12 AM",
    "link": "/gp/video/detail/B0DDQ6NF7C/ref=atv_hm_liv_c_czP1UB_1_47?jic=8%7CEgNhbGw%3D",
    "status": "UPCOMING"
  },
  {
    "display_title": "SV Werder Bremen vs. RasenBallsport Leipzig",
    "title": "SV Werder Bremen vs. RasenBallsport Leipzig",
    "titleID": "B0DK4774HK",
    "synopsis": "Watch SV Werder Bremen take on RasenBallsport Leipzig",
    "poster": "https://m.media-amazon.com/images/S/le-target-images-prod/amzn1.dv.gti.4fe794d1-f42b-4b68-bea4-9d4d042933a5/3/BOXART-16X9/en-US._UR1920,1080_.png",
    "liveinfo": "UPCOMING",
    "time_badge": "Tomorrow 9:12 AM",
    "link": "/gp/video/detail/B0DK4774HK/ref=atv_hm_liv_c_czP1UB_1_48?jic=8%7CEgNhbGw%3D",
    "status": "UPCOMING"
  },
  {
    "display_title": "VfL Bochum 1848 vs. 1. FSV Mainz 05",
    "title": "VfL Bochum 1848 vs. 1. FSV Mainz 05",
    "titleID": "B0F63K4C3D",
    "synopsis": "Watch VfL Bochum 1848 take on 1. FSV Mainz 05",
    "poster": "https://m.media-amazon.com/images/S/le-target-images-prod/amzn1.dv.gti.8e456faa-f73b-4b70-8012-24b3dfa40631/1/BOXART-16X9/en-US._UR1920,1080_.png",
    "liveinfo": "UPCOMING",
    "time_badge": "Tomorrow 9:12 AM",
    "link": "/gp/video/detail/B0F63K4C3D/ref=atv_hm_liv_c_czP1UB_1_49?jic=8%7CEgNhbGw%3D",
    "status": "UPCOMING"
  },
  {
    "display_title": "Kieler SV Holstein 1900 vs. SC Freiburg",
    "title": "Kieler SV Holstein 1900 vs. SC Freiburg",
    "titleID": "B0F3VJFDJX",
    "synopsis": "Watch Kieler SV Holstein 1900 take on SC Freiburg",
    "poster": "https://m.media-amazon.com/images/S/le-target-images-prod/amzn1.dv.gti.99b6da36-60dc-44e2-a5a8-faa938af5a52/1/BOXART-16X9/en-US._UR1920,1080_.png",
    "liveinfo": "UPCOMING",
    "time_badge": "Tomorrow 9:12 AM",
    "link": "/gp/video/detail/B0F3VJFDJX/ref=atv_hm_liv_c_czP1UB_1_50?jic=8%7CEgNhbGw%3D",
    "status": "UPCOMING"
  },
  {
    "display_title": "Truist Championship, Third Round",
    "title": "Truist Championship, Third Round",
    "titleID": "B0F4P6NM6T",
    "synopsis": "From The Philadelphia Cricket Club (Wissahickon Course) in Philadelphia.",
    "poster": "https://m.media-amazon.com/images/S/le-target-images-prod/amzn1.dv.gti.d10e544c-b4cd-4f1e-b4e0-94e8503baa84/1/BOXART-16X9/en-US._UR1920,1080_.jpg",
    "liveinfo": "UPCOMING",
    "time_badge": "Tomorrow 2:55 PM",
    "link": "/gp/video/detail/B0F4P6NM6T/ref=atv_hm_liv_c_czP1UB_1_91?jic=8%7CEgNhbGw%3D",
    "status": "UPCOMING"
  },
  {
    "display_title": "Celtics at Knicks",
    "title": "Celtics at Knicks",
    "titleID": "B0F7DVYWXZ",
    "synopsis": "NBA Playoffs: Watch the Boston Celtics and the New York Knicks face off at Madison Square Garden broadcasting live from New York!",
    "poster": "https://m.media-amazon.com/images/S/le-target-images-prod/amzn1.dv.gti.35d562b9-fbb6-4260-a254-8b16a7a84911/58/BOXART-16X9/en-US/1920x1080._UR1920,1080_.png",
    "liveinfo": "UPCOMING",
    "time_badge": "Tomorrow 3:25 PM",
    "link": "/gp/video/detail/B0F7DVYWXZ/ref=atv_hm_liv_c_czP1UB_1_92?jic=8%7CEgNhbGw%3D",
    "status": "UPCOMING"
  },
  {
    "display_title": "QMJHL Playoffs: Rimouski Oceanic vs. Moncton Wildcats - Game 1",
    "title": "QMJHL Playoffs: Rimouski Oceanic vs. Moncton Wildcats - Game 1",
    "titleID": "B0F798R7GN",
    "synopsis": "From Sun Life Financial Coliseum in Rimouski, Québec.",
    "poster": "https://m.media-amazon.com/images/S/le-target-images-prod/amzn1.dv.gti.fbb20297-ce99-4248-848f-9b3c1a6e2379/11/BOXART-16X9/en-US._UR1920,1080_.jpg",
    "liveinfo": "UPCOMING",
    "time_badge": "Tomorrow 3:55 PM",
    "link": "/gp/video/detail/B0F798R7GN/ref=atv_hm_liv_c_czP1UB_1_93?jic=8%7CEgNhbGw%3D",
    "status": "UPCOMING"
  },
  {
    "display_title": "Braves at Pirates",
    "title": "Braves at Pirates",
    "titleID": "B0F1XSYNLN",
    "synopsis": "Watch Braves at Pirates LIVE from Pittsburgh.",
    "poster": "https://m.media-amazon.com/images/S/le-target-images-prod/amzn1.dv.gti.c24fe114-9576-4316-bfb7-64c1bf9ce1c0/108/BOXART-16X9/en-US._UR1920,1080_.png",
    "liveinfo": "UPCOMING",
    "time_badge": "Tomorrow 4:05 PM",
    "link": "/gp/video/detail/B0F1XSYNLN/ref=atv_hm_liv_c_czP1UB_1_94?jic=8%7CEgNhbGw%3D",
    "status": "UPCOMING"
  },
  {
    "display_title": "Yankees at Athletics",
    "title": "Yankees at Athletics",
    "titleID": "B0DRQVYCXL",
    "synopsis": "Watch Yankees at Athletics LIVE from West Sacramento.",
    "poster": "https://m.media-amazon.com/images/S/le-target-images-prod/amzn1.dv.gti.cdf1012c-e322-4581-9a6c-a0a95c78f779/110/BOXART-16X9/en-US._UR1920,1080_.png",
    "liveinfo": "UPCOMING",
    "time_badge": "Tomorrow 4:05 PM",
    "link": "/gp/video/detail/B0DRQVYCXL/ref=atv_hm_liv_c_czP1UB_1_95?jic=8%7CEgNhbGw%3D",
    "status": "UPCOMING"
  },
  {
    "display_title": "Cardinals at Nationals",
    "title": "Cardinals at Nationals",
    "titleID": "B0DV9GV4FT",
    "synopsis": "Watch Cardinals at Nationals LIVE from Washington.",
    "poster": "https://m.media-amazon.com/images/S/le-target-images-prod/amzn1.dv.gti.db6b4cdd-cfd7-4388-b705-e48899c2341f/120/BOXART-16X9/en-US._UR1920,1080_.png",
    "liveinfo": "UPCOMING",
    "time_badge": "Tomorrow 4:05 PM",
    "link": "/gp/video/detail/B0DV9GV4FT/ref=atv_hm_liv_c_czP1UB_1_96?jic=8%7CEgNhbGw%3D",
    "status": "UPCOMING"
  },
  {
    "display_title": "Brewers at Rays",
    "title": "Brewers at Rays",
    "titleID": "B0F5M747BB",
    "synopsis": "Watch Brewers at Rays LIVE from Tampa.",
    "poster": "https://m.media-amazon.com/images/S/le-target-images-prod/amzn1.dv.gti.01f04656-defe-4521-8aad-a5c23d611fc9/105/BOXART-16X9/en-US._UR1920,1080_.png",
    "liveinfo": "UPCOMING",
    "time_badge": "Tomorrow 4:10 PM",
    "link": "/gp/video/detail/B0F5M747BB/ref=atv_hm_liv_c_czP1UB_1_97?jic=8%7CEgNhbGw%3D",
    "status": "UPCOMING"
  },
  {
    "display_title": "Sonsio Grand Prix",
    "title": "Sonsio Grand Prix",
    "titleID": "B0DWL9YJHC",
    "synopsis": "Watch Sonsio Grand Prix: Race venue: Indianapolis Motor Speedway",
    "poster": "https://m.media-amazon.com/images/S/le-target-images-prod/amzn1.dv.gti.867b8b09-d3d4-4036-b102-001fe4c55872/5/BOXART-16X9/en-US._UR1920,1080_.jpg",
    "liveinfo": "UPCOMING",
    "time_badge": "Tomorrow 4:25 PM",
    "link": "/gp/video/detail/B0DWL9YJHC/ref=atv_hm_liv_c_czP1UB_1_98?jic=8%7CEgNhbGw%3D",
    "status": "UPCOMING"
  },
  {
    "display_title": "NASCAR Cup Series at Kansas",
    "title": "NASCAR Cup Series at Kansas",
    "titleID": "B0F4QZL1H2",
    "synopsis": "Watch NASCAR Cup Series at Kansas: Kansas Practice & Qualifying in Kansas City venue: Kansas Speedway",
    "poster": "https://m.media-amazon.com/images/S/le-target-images-prod/amzn1.dv.gti.bd591e20-f0df-407c-9561-b6d1ceafaf6e/3/BOXART-16X9/en-US._UR1920,1080_.jpg",
    "liveinfo": "UPCOMING",
    "time_badge": "Tomorrow 4:25 PM",
    "link": "/gp/video/detail/B0F4QZL1H2/ref=atv_hm_liv_c_czP1UB_1_99?jic=8%7CEgNhbGw%3D",
    "status": "UPCOMING"
  },
  {
    "display_title": "Bay Breakers vs. Boston Banshees",
    "title": "Bay Breakers vs. Boston Banshees",
    "titleID": "B0DPL623TB",
    "synopsis": "Watch the latest Women's Elite Rugby action from the United States, live on DAZN.",
    "poster": "https://m.media-amazon.com/images/S/le-target-images-prod/amzn1.dv.gti.b18e1acd-09bb-4e0a-a4ab-3d57275fa537/1/BOXART-16X9/en-US._UR1920,1080_.png",
    "liveinfo": "UPCOMING",
    "time_badge": "Tomorrow 4:40 PM",
    "link": "/gp/video/detail/B0DPL623TB/ref=atv_hm_liv_c_czP1UB_1_100?jic=8%7CEgNhbGw%3D",
    "status": "UPCOMING"
  },
  {
    "display_title": "New York City Football Club vs. CF Montréal",
    "title": "New York City Football Club vs. CF Montréal",
    "titleID": "B0DJMSVL2C",
    "synopsis": "Watch NYC host Montréal",
    "poster": "https://m.media-amazon.com/images/S/le-target-images-prod/amzn1.dv.gti.a6deeda2-d231-4f88-8963-c8e6fe08634a/3/BOXART-16X9/en-US/1920x1080._UR1920,1080_.png",
    "liveinfo": "UPCOMING",
    "time_badge": "Tomorrow 7:30 PM",
    "link": "/gp/video/detail/B0DJMSVL2C/ref=atv_hm_liv_c_czP1UB_1_121?jic=8%7CEgNhbGw%3D",
    "status": "UPCOMING"
  },
  {
    "display_title": "Philadelphia Union vs. Columbus Crew",
    "title": "Philadelphia Union vs. Columbus Crew",
    "titleID": "B0F6MLYBMY",
    "synopsis": "Watch the Union host the Crew",
    "poster": "https://m.media-amazon.com/images/S/le-target-images-prod/amzn1.dv.gti.abc0eaf4-fa34-4019-b668-b7937f73697f/3/BOXART-16X9/en-US/1920x1080._UR1920,1080_.png",
    "liveinfo": "UPCOMING",
    "time_badge": "Tomorrow 7:30 PM",
    "link": "/gp/video/detail/B0F6MLYBMY/ref=atv_hm_liv_c_czP1UB_1_122?jic=8%7CEgNhbGw%3D",
    "status": "UPCOMING"
  },
  {
    "display_title": "MLS 360 En Español",
    "title": "MLS 360 En Español",
    "titleID": "B0DSJQDBM2",
    "synopsis": "Jump around the league for highlights and analysis from the matchday as they happen. (En español)",
    "poster": "https://m.media-amazon.com/images/S/le-target-images-prod/amzn1.dv.gti.07607ad8-55fe-44e3-a093-0abdb966c4a0/1/BOXART-16X9/en-US._UR1920,1080_.jpeg",
    "liveinfo": "UPCOMING",
    "time_badge": "Tomorrow 7:30 PM",
    "link": "/gp/video/detail/B0DSJQDBM2/ref=atv_hm_liv_c_czP1UB_1_123?jic=8%7CEgNhbGw%3D",
    "status": "UPCOMING"
  },
  {
    "display_title": "MLS 360",
    "title": "MLS 360",
    "titleID": "B0DSJPKBX1",
    "synopsis": "Jump around the league for highlights and analysis from the matchday as they happen.",
    "poster": "https://m.media-amazon.com/images/S/le-target-images-prod/amzn1.dv.gti.e2310a1e-ec7f-4eee-a3f4-6f6ecf9563d1/1/BOXART-16X9/en-US._UR1920,1080_.jpeg",
    "liveinfo": "UPCOMING",
    "time_badge": "Tomorrow 7:30 PM",
    "link": "/gp/video/detail/B0DSJPKBX1/ref=atv_hm_liv_c_czP1UB_1_124?jic=8%7CEgNhbGw%3D",
    "status": "UPCOMING"
  },
  {
    "display_title": "The Party Animals vs. Savannah Bananas",
    "title": "The Party Animals vs. Savannah Bananas",
    "titleID": "B0F625ZJS4",
    "synopsis": "From Nissan Stadium in Nashville, Tenn.",
    "poster": "https://m.media-amazon.com/images/S/le-target-images-prod/amzn1.dv.gti.45f70271-65ad-4088-848c-efae29bbd5d8/2/BOXART-16X9/en-US._UR1920,1080_.jpg",
    "liveinfo": "UPCOMING",
    "time_badge": "Tomorrow 7:55 PM",
    "link": "/gp/video/detail/B0F625ZJS4/ref=atv_hm_liv_c_czP1UB_1_125?jic=8%7CEgNhbGw%3D",
    "status": "UPCOMING"
  },
  {
    "display_title": "Flex Fight Series-Vol.46",
    "title": "Flex Fight Series-Vol.46",
    "titleID": "B0DYBZ2Z1M",
    "synopsis": "NY's Biggest combat sports brand presents a night of championship MMA & Kickboxing from Selden VFD Training Center on Long Island.",
    "poster": "https://m.media-amazon.com/images/S/le-target-images-prod/amzn1.dv.gti.7ff21463-3e0d-44c2-9a50-8faa12d7b0a5/2/BOXART-16X9/en-US._UR1920,1080_.jpg",
    "liveinfo": "UPCOMING",
    "time_badge": "Tomorrow 7:55 PM",
    "link": "/gp/video/detail/B0DYBZ2Z1M/ref=atv_hm_liv_c_czP1UB_1_126?jic=8%7CEgNhbGw%3D",
    "status": "UPCOMING"
  },
  {
    "display_title": "Richman vs. Dyer",
    "title": "Richman vs. Dyer",
    "titleID": "B0F7G98FBZ",
    "synopsis": "Salt Lake City is the battleground as Mike 'The Marine' Richman goes to war with Josh 'D-Day' Dyer for the light heavyweight title.",
    "poster": "https://m.media-amazon.com/images/S/le-target-images-prod/amzn1.dv.gti.5741db99-d763-4867-b58b-6548351a0623/4/BOXART-16X9/en-US._UR1920,1080_.jpeg",
    "liveinfo": "UPCOMING",
    "time_badge": "Tomorrow 7:57 PM",
    "link": "/gp/video/detail/B0F7G98FBZ/ref=atv_hm_liv_c_czP1UB_1_127?jic=8%7CEgNhbGw%3D",
    "status": "UPCOMING"
  },
  {
    "display_title": "Padres at Rockies",
    "title": "Padres at Rockies",
    "titleID": "B0F441B155",
    "synopsis": "Watch Padres at Rockies LIVE from Denver.",
    "poster": "https://m.media-amazon.com/images/S/le-target-images-prod/amzn1.dv.gti.038228a2-a01a-4ce0-a59a-e81c5c1bd618/110/BOXART-16X9/en-US._UR1920,1080_.png",
    "liveinfo": "UPCOMING",
    "time_badge": "Tomorrow 8:10 PM",
    "link": "/gp/video/detail/B0F441B155/ref=atv_hm_liv_c_czP1UB_1_128?jic=8%7CEgNhbGw%3D",
    "status": "UPCOMING"
  },
  {
    "display_title": "Dodgers at Diamondbacks",
    "title": "Dodgers at Diamondbacks",
    "titleID": "B0DPBZ778W",
    "synopsis": "Watch Dodgers at Diamondbacks LIVE from Phoenix.",
    "poster": "https://m.media-amazon.com/images/S/le-target-images-prod/amzn1.dv.gti.465202dd-5775-4d52-9bd2-73a092a2ac76/114/BOXART-16X9/en-US._UR1920,1080_.png",
    "liveinfo": "UPCOMING",
    "time_badge": "Tomorrow 8:10 PM",
    "link": "/gp/video/detail/B0DPBZ778W/ref=atv_hm_liv_c_czP1UB_1_129?jic=8%7CEgNhbGw%3D",
    "status": "UPCOMING"
  },
  {
    "display_title": "Timberwolves at Warriors",
    "title": "Timberwolves at Warriors",
    "titleID": "B0DYPJ2NKJ",
    "synopsis": "NBA Playoffs: Watch the Minnesota Timberwolves and the Golden State Warriors face off at Chase Center broadcasting live from San Francisco!",
    "poster": "https://m.media-amazon.com/images/S/le-target-images-prod/amzn1.dv.gti.a50c8d25-c772-45e6-85c2-c42287fc3152/47/BOXART-16X9/en-US/1920x1080._UR1920,1080_.png",
    "liveinfo": "UPCOMING",
    "time_badge": "Tomorrow 8:25 PM",
    "link": "/gp/video/detail/B0DYPJ2NKJ/ref=atv_hm_liv_c_czP1UB_1_130?jic=8%7CEgNhbGw%3D",
    "status": "UPCOMING"
  },
  {
    "display_title": "Bundesliga: Goal Arena",
    "title": "Bundesliga: Goal Arena",
    "titleID": "B0F4MWNGCZ",
    "synopsis": "Keep across the action from four Bundesliga matches on matchday 33, as struggling Holstein Kiel and VfL Bochum host Freiburg and Mainz respectively. Elsewhere, RB Leipzig travels to Werder Bremen and Union Berlin takes on Hoffenheim.",
    "poster": "https://m.media-amazon.com/images/S/le-target-images-prod/amzn1.dv.gti.b6af91ca-3ce7-4240-83fb-89d735e8b109/1/BOXART-16X9/en-US._UR1920,1080_.png",
    "liveinfo": "UPCOMING",
    "time_badge": "Tomorrow 9:12 AM",
    "link": "/gp/video/detail/B0F4MWNGCZ/ref=atv_hm_liv_c_czP1UB_1_51?jic=8%7CEgNhbGw%3D",
    "status": "UPCOMING"
  },
  {
    "display_title": "Fulham FC vs. Everton FC",
    "title": "Fulham FC vs. Everton FC",
    "titleID": "B0F6T86C56",
    "synopsis": "Watch Fulham FC take on Everton FC",
    "poster": "https://m.media-amazon.com/images/S/le-target-images-prod/amzn1.dv.gti.3125f6fe-636f-4298-a02c-05218d15bf71/2/BOXART-16X9/en-US._UR1920,1080_.jpg",
    "liveinfo": "UPCOMING",
    "time_badge": "Tomorrow 9:40 AM",
    "link": "/gp/video/detail/B0F6T86C56/ref=atv_hm_liv_c_czP1UB_1_52?jic=8%7CEgNhbGw%3D",
    "status": "UPCOMING"
  },
  {
    "display_title": "Southampton FC vs. Manchester City FC",
    "title": "Southampton FC vs. Manchester City FC",
    "titleID": "B0DZSW7CGT",
    "synopsis": "Watch Southampton FC take on Manchester City FC",
    "poster": "https://m.media-amazon.com/images/S/le-target-images-prod/amzn1.dv.gti.5ff2e9ea-67d3-4f58-9ea6-5a04853aad02/3/BOXART-16X9/en-US._UR1920,1080_.jpg",
    "liveinfo": "UPCOMING",
    "time_badge": "Tomorrow 9:40 AM",
    "link": "/gp/video/detail/B0DZSW7CGT/ref=atv_hm_liv_c_czP1UB_1_53?jic=8%7CEgNhbGw%3D",
    "status": "UPCOMING"
  },
  {
    "display_title": "Wolverhampton Wanderers FC vs. Brighton & Hove Albion FC",
    "title": "Wolverhampton Wanderers FC vs. Brighton & Hove Albion FC",
    "titleID": "B0DSF29FKJ",
    "synopsis": "Watch Wolverhampton Wanderers FC take on Brighton & Hove Albion FC",
    "poster": "https://m.media-amazon.com/images/S/le-target-images-prod/amzn1.dv.gti.d3308711-4a39-4974-8c7e-e610c0f4f077/2/BOXART-16X9/en-US._UR1920,1080_.jpg",
    "liveinfo": "UPCOMING",
    "time_badge": "Tomorrow 9:40 AM",
    "link": "/gp/video/detail/B0DSF29FKJ/ref=atv_hm_liv_c_czP1UB_1_54?jic=8%7CEgNhbGw%3D",
    "status": "UPCOMING"
  },
  {
    "display_title": "Ipswich Town FC vs. Brentford FC",
    "title": "Ipswich Town FC vs. Brentford FC",
    "titleID": "B0F1MPT6VL",
    "synopsis": "Watch Ipswich Town FC take on Brentford FC",
    "poster": "https://m.media-amazon.com/images/S/le-target-images-prod/amzn1.dv.gti.d4e88f60-a9bd-47ab-a89d-be411213aac6/3/BOXART-16X9/en-US._UR1920,1080_.jpg",
    "liveinfo": "UPCOMING",
    "time_badge": "Tomorrow 9:40 AM",
    "link": "/gp/video/detail/B0F1MPT6VL/ref=atv_hm_liv_c_czP1UB_1_55?jic=8%7CEgNhbGw%3D",
    "status": "UPCOMING"
  },
  {
    "display_title": "Semifinal: Belarus vs. Senegal",
    "title": "Semifinal: Belarus vs. Senegal",
    "titleID": "B0F584BP5F",
    "synopsis": "From Paradise Arena, in Victoria, Seychelles.",
    "poster": "https://m.media-amazon.com/images/S/le-target-images-prod/amzn1.dv.gti.7a6418ba-0a17-40f7-a128-921404c313b9/94/BOXART-16X9/en-US._UR1920,1080_.jpg",
    "liveinfo": "UPCOMING",
    "time_badge": "Tomorrow 9:43 AM",
    "link": "/gp/video/detail/B0F584BP5F/ref=atv_hm_liv_c_czP1UB_1_56?jic=8%7CEgNhbGw%3D",
    "status": "UPCOMING"
  },
  {
    "display_title": "Indian Premier League 2025 - 60th Match - Sunrisers Hyderabad vs Kolkata Knight Riders",
    "title": "Indian Premier League 2025 - 60th Match - Sunrisers Hyderabad vs Kolkata Knight Riders",
    "titleID": "B0F32MBJBC",
    "synopsis": "Indian Premier League 2025 - 60th Match - Sunrisers Hyderabad vs Kolkata Knight Riders",
    "poster": "https://m.media-amazon.com/images/S/le-target-images-prod/amzn1.dv.gti.0eb411d3-d734-42f0-840d-d1757541a4ad/2/BOXART-16X9/en-US._UR1920,1080_.jpeg",
    "liveinfo": "UPCOMING",
    "time_badge": "Tomorrow 9:55 AM",
    "link": "/gp/video/detail/B0F32MBJBC/ref=atv_hm_liv_c_czP1UB_1_57?jic=8%7CEgNhbGw%3D",
    "status": "UPCOMING"
  },
  {
    "display_title": "Germany vs. Hungary",
    "title": "Germany vs. Hungary",
    "titleID": "B0F2TK9BWK",
    "synopsis": "Group B.",
    "poster": "https://m.media-amazon.com/images/S/le-target-images-prod/amzn1.dv.gti.25720597-c1e3-4ade-86b1-661a30b59144/8/BOXART-16X9/en-US._UR1920,1080_.jpg",
    "liveinfo": "UPCOMING",
    "time_badge": "Tomorrow 9:55 AM",
    "link": "/gp/video/detail/B0F2TK9BWK/ref=atv_hm_liv_c_czP1UB_1_58?jic=8%7CEgNhbGw%3D",
    "status": "UPCOMING"
  },
  {
    "display_title": "PTT Boca Raton Men - Day 6",
    "title": "PTT Boca Raton Men - Day 6",
    "titleID": "B0F4MVZT4D",
    "synopsis": "PTT Boca Raton Men - Day 6",
    "poster": "https://m.media-amazon.com/images/S/le-target-images-prod/amzn1.dv.gti.5362b77e-0c64-4f1b-96c9-795b3a9c15e9/3/BOXART-16X9/en-US._UR1920,1080_.png",
    "liveinfo": "UPCOMING",
    "time_badge": "Tomorrow 9:55 AM",
    "link": "/gp/video/detail/B0F4MVZT4D/ref=atv_hm_liv_c_czP1UB_1_59?jic=8%7CEgNhbGw%3D",
    "status": "UPCOMING"
  },
  {
    "display_title": "Sweden vs. Austria",
    "title": "Sweden vs. Austria",
    "titleID": "B0DYZ6BKKQ",
    "synopsis": "Group A.",
    "poster": "https://m.media-amazon.com/images/S/le-target-images-prod/amzn1.dv.gti.67f601c4-04ab-43f0-8fb2-0e7d01bd081e/84/BOXART-16X9/en-US._UR1920,1080_.jpg",
    "liveinfo": "UPCOMING",
    "time_badge": "Tomorrow 9:55 AM",
    "link": "/gp/video/detail/B0DYZ6BKKQ/ref=atv_hm_liv_c_czP1UB_1_60?jic=8%7CEgNhbGw%3D",
    "status": "UPCOMING"
  }
]